[{"player": "Borja V\u00e1zquez", "position": "RW", "target": "P. Ferrer", "target_pos": "CF", "minute": 10, "period": 1, "flank": "wide_right", "x_start": 19.74, "y_start": -24.67, "x_end": 37.13, "y_end": -5.2, "high_pass": false, "lead_to_shot": false, "lead_to_goal": false, "outcome": "unsuccessful"}, {"player": "Eneko Undabarrena", "position": "LCB", "target": "David And\u00fajar", "target_pos": "RCB", "minute": 12, "period": 1, "flank": "wide_left", "x_start": -12.99, "y_start": 21.9, "x_end": -21.29, "y_end": -6.09, "high_pass": false, "lead_to_shot": false, "lead_to_goal": false, "outcome": "successful"}, {"player": "David And\u00fajar", "position": "RCB", "target": "Andr\u00e9s Prieto", "target_pos": "GK", "minute": 18, "period": 1, "flank": "wide_right", "x_start": -10.42, "y_start": -20.47, "x_end": -40.28, "y_end": -3.68, "high_pass": false, "lead_to_shot": false, "lead_to_goal": false, "outcome": "successful"}, {"player": "Eneko Undabarrena", "position": "LCB", "target": "David And\u00fajar", "target_pos": "RCB", "minute": 18, "period": 1, "flank": "wide_left", "x_start": -12.16, "y_start": 20.23, "x_end": -19.19, "y_end": -7.77, "high_pass": false, "lead_to_shot": false, "lead_to_goal": false, "outcome": "successful"}, {"player": "Borja Valle", "position": "LW", "target": "Eneko Undabarrena", "target_pos": "LCB", "minute": 19, "period": 1, "flank": "wide_left", "x_start": 25.27, "y_start": 22.3, "x_end": 5.93, "y_end": 10.37, "high_pass": false, "lead_to_shot": false, "lead_to_goal": false, "outcome": "successful"}, {"player": "Andoni L\u00f3pez", "position": "LB", "target": "P. Ferrer", "target_pos": "CF", "minute": 19, "period": 1, "flank": "wide_left", "x_start": 24.37, "y_start": 32.82, "x_end": 41.01, "y_end": 5.82, "high_pass": true, "lead_to_shot": false, "lead_to_goal": false, "outcome": "successful"}, {"player": "David And\u00fajar", "position": "RCB", "target": "Eneko Undabarrena", "target_pos": "LCB", "minute": 32, "period": 1, "flank": "wide_right", "x_start": -14.77, "y_start": -21.86, "x_end": -14.64, "y_end": 7.81, "high_pass": false, "lead_to_shot": false, "lead_to_goal": false, "outcome": "successful"}, {"player": "Borja V\u00e1zquez", "position": "RW", "target": "P. Ferrer", "target_pos": "CF", "minute": 35, "period": 1, "flank": "wide_right", "x_start": 41.77, "y_start": -25.87, "x_end": 42.73, "y_end": 6.02, "high_pass": false, "lead_to_shot": false, "lead_to_goal": false, "outcome": "unsuccessful"}, {"player": "Andoni L\u00f3pez", "position": "LB", "target": "P. Ferrer", "target_pos": "CF", "minute": 42, "period": 1, "flank": "wide_left", "x_start": 2.3, "y_start": 23.21, "x_end": 44.08, "y_end": -1.69, "high_pass": true, "lead_to_shot": true, "lead_to_goal": false, "outcome": "successful"}, {"player": "Andoni L\u00f3pez", "position": "LB", "target": "Jos\u00e9 Luis Cort\u00e9s", "target_pos": "CF", "minute": 44, "period": 1, "flank": "wide_left", "x_start": 31.83, "y_start": 30.74, "x_end": 44.7, "y_end": 6.8, "high_pass": false, "lead_to_shot": true, "lead_to_goal": false, "outcome": "successful"}, {"player": "David And\u00fajar", "position": "RCB", "target": "Eneko Undabarrena", "target_pos": "LCB", "minute": 45, "period": 1, "flank": "wide_right", "x_start": -6.96, "y_start": -22.26, "x_end": -5.22, "y_end": 6.72, "high_pass": false, "lead_to_shot": false, "lead_to_goal": false, "outcome": "successful"}, {"player": "Andoni L\u00f3pez", "position": "LB", "target": "P. Ferrer", "target_pos": "CF", "minute": 48, "period": 2, "flank": "wide_left", "x_start": 22.0, "y_start": 25.88, "x_end": 37.91, "y_end": 1.22, "high_pass": false, "lead_to_shot": false, "lead_to_goal": false, "outcome": "unsuccessful"}, {"player": "Borja Valle", "position": "LW", "target": "E. Frimpong", "target_pos": "LM", "minute": 49, "period": 2, "flank": "wide_left", "x_start": 37.09, "y_start": 23.07, "x_end": 30.22, "y_end": 2.64, "high_pass": false, "lead_to_shot": true, "lead_to_goal": false, "outcome": "successful"}, {"player": "Andoni L\u00f3pez", "position": "LB", "target": "Fede San Emeterio", "target_pos": "RM", "minute": 51, "period": 2, "flank": "wide_left", "x_start": 5.52, "y_start": 31.56, "x_end": 7.64, "y_end": -0.99, "high_pass": false, "lead_to_shot": false, "lead_to_goal": false, "outcome": "successful"}, {"player": "Andoni L\u00f3pez", "position": "LB", "target": "P. Ferrer", "target_pos": "CF", "minute": 51, "period": 2, "flank": "wide_left", "x_start": 22.02, "y_start": 23.76, "x_end": 40.32, "y_end": -1.33, "high_pass": false, "lead_to_shot": false, "lead_to_goal": false, "outcome": "unsuccessful"}, {"player": "Borja V\u00e1zquez", "position": "RW", "target": "P. Ferrer", "target_pos": "CF", "minute": 52, "period": 2, "flank": "wide_right", "x_start": 30.76, "y_start": -29.44, "x_end": 43.99, "y_end": -6.39, "high_pass": true, "lead_to_shot": false, "lead_to_goal": false, "outcome": "successful"}, {"player": "Borja V\u00e1zquez", "position": "RW", "target": null, "target_pos": null, "minute": 54, "period": 2, "flank": "wide_right", "x_start": 11.01, "y_start": -32.5, "x_end": 43.7, "y_end": -15.01, "high_pass": false, "lead_to_shot": true, "lead_to_goal": true, "outcome": null}, {"player": "Borja V\u00e1zquez", "position": "RW", "target": "A. Keita", "target_pos": "CF", "minute": 85, "period": 2, "flank": "wide_right", "x_start": 33.35, "y_start": -25.4, "x_end": 47.65, "y_end": -5.96, "high_pass": false, "lead_to_shot": false, "lead_to_goal": false, "outcome": "unsuccessful"}, {"player": "A. Keita", "position": "CF", "target": null, "target_pos": null, "minute": 90, "period": 2, "flank": "wide_right", "x_start": 23.11, "y_start": -32.42, "x_end": 52.04, "y_end": -17.02, "high_pass": false, "lead_to_shot": false, "lead_to_goal": false, "outcome": null}]