[{"n":"Eneko Undabarrena","p":1,"min":0,"dir":"b","rng":"m","dist":20.4,"out":"s","third":"d","tthird":"d","high":1,"gs":"d","pos":"LCB","press":"np","xp":0.931,"byp":0,"phase":"di","ch":"c","x":-16.9,"y":-6.7,"xe":-36.7,"ye":-2.0,"to":"Andr\u00e9s Prieto"},{"n":"Andr\u00e9s Prieto","p":1,"min":0,"dir":"f","rng":"l","dist":69.0,"out":"s","third":"d","tthird":"a","slb":1,"high":1,"one":1,"ahead":1,"gs":"d","pos":"GK","xp":0.866,"xt":0.001,"byp":5,"phase":"fi","ch":"c","x":-36.7,"y":-2.0,"xe":27.6,"ye":-27.3,"to":"Carlos Calder\u00f3n"},{"n":"E. Frimpong","p":1,"min":0,"dir":"sl","rng":"l","dist":30.6,"out":"s","third":"m","tthird":"m","gs":"d","pos":"LM","press":"lp","xp":0.986,"xt":0.0029,"byp":-1,"phase":"cr","ch":"hr","x":8.7,"y":-14.2,"xe":-3.0,"ye":14.1,"to":"Andoni L\u00f3pez"},{"n":"Andoni L\u00f3pez","p":1,"min":0,"dir":"sr","rng":"m","dist":28.3,"out":"s","third":"m","tthird":"m","gs":"d","pos":"LB","press":"np","xp":0.999,"xt":0.0003,"byp":0,"phase":"cr","ch":"hl","x":-3.8,"y":20.4,"xe":-14.8,"ye":-5.8,"to":"Eneko Undabarrena"},{"n":"Eneko Undabarrena","p":1,"min":0,"dir":"sr","rng":"m","dist":21.5,"out":"s","third":"m","tthird":"m","ahead":1,"gs":"d","pos":"LCB","press":"np","xp":0.998,"xt":0.0004,"byp":0,"phase":"cr","ch":"c","x":-14.0,"y":-9.1,"xe":-6.7,"ye":-29.3,"to":"Koke"},{"n":"Koke","p":1,"min":0,"dir":"sl","rng":"s","dist":8.2,"out":"s","third":"m","tthird":"m","ahead":1,"gs":"d","pos":"RB","press":"lp","xp":0.98,"xt":0.0005,"byp":2,"phase":"cr","ch":"wr","x":-9.5,"y":-27.9,"xe":-6.8,"ye":-20.2,"to":"Vicente Esquerdo"},{"n":"Vicente Esquerdo","p":1,"min":0,"dir":"b","rng":"s","dist":12.4,"out":"s","third":"m","tthird":"m","one":1,"gs":"d","pos":"CM","press":"mp","xp":0.958,"xt":0.0002,"byp":-2,"phase":"cr","ch":"wr","x":-6.8,"y":-20.2,"xe":-17.0,"ye":-27.2,"to":"Koke"},{"n":"Koke","p":1,"min":0,"dir":"b","rng":"s","dist":14.4,"out":"s","third":"m","tthird":"d","gs":"d","pos":"RB","press":"lp","xp":0.995,"xt":0.0001,"byp":0,"phase":"bu","ch":"wr","x":-24.5,"y":-28.7,"xe":-34.8,"ye":-18.5,"to":"Eneko Undabarrena"},{"n":"Eneko Undabarrena","p":1,"min":0,"dir":"f","rng":"l","dist":38.6,"out":"s","third":"d","tthird":"m","slb":1,"high":1,"ahead":1,"diff":1,"gs":"d","pos":"LCB","xp":0.606,"xt":0.0008,"byp":5,"phase":"bu","ch":"hr","x":-34.7,"y":-19.4,"xe":2.7,"ye":-29.2,"to":"Carlos Calder\u00f3n"},{"n":"Koke","p":1,"min":0,"dir":"f","rng":"m","dist":15.3,"out":"s","third":"m","tthird":"m","flb":1,"one":1,"ahead":1,"gs":"d","pos":"RB","press":"lp","xp":0.951,"xt":0.0019,"byp":4,"phase":"qb","ch":"hr","x":-5.4,"y":-14.0,"xe":8.8,"ye":-19.4,"to":"Carlos Calder\u00f3n"},{"n":"Carlos Calder\u00f3n","p":1,"min":0,"tdir":"f","out":"u","third":"m","dng":1,"ahead":1,"diff":1,"gs":"d","pos":"RF","press":"lp","xp":0.251,"xt":0.0268,"byp":2,"phase":"qb","ch":"hr","x":27.5,"y":-31.2,"xe":32.9,"ye":-8.1,"to":"A. Keita"},{"n":"Koke","p":1,"min":1,"dir":"sl","rng":"s","dist":7.6,"out":"s","third":"a","tthird":"a","gs":"d","pos":"RB","press":"lp","xp":0.962,"xt":0.003,"byp":0,"phase":"fi","ch":"wr","x":26.6,"y":-29.3,"xe":21.4,"ye":-23.9,"to":"Vicente Esquerdo"},{"n":"Vicente Esquerdo","p":1,"min":1,"dir":"sl","rng":"m","dist":17.1,"out":"s","third":"a","tthird":"a","ahead":1,"gs":"d","pos":"CM","press":"mp","xp":0.834,"xt":0.0152,"byp":3,"phase":"fi","ch":"wr","x":20.9,"y":-19.7,"xe":26.1,"ye":-3.4,"to":"Borja V\u00e1zquez"},{"n":"Borja V\u00e1zquez","p":1,"min":1,"dir":"b","rng":"s","dist":14.2,"out":"s","third":"a","tthird":"m","one":1,"gs":"d","pos":"RM","press":"hp","xp":0.945,"xt":0.0037,"byp":-4,"phase":"fi","ch":"c","x":26.1,"y":-3.4,"xe":12.2,"ye":-6.5,"to":"E. Frimpong"},{"n":"E. Frimpong","p":1,"min":1,"tdir":"sl","out":"u","third":"m","llb":1,"slb":1,"dng":1,"ahead":1,"diff":1,"gs":"d","pos":"LM","xp":0.389,"xt":0.0821,"byp":6,"phase":"fi","ch":"c","x":19.9,"y":2.9,"xe":34.9,"ye":-5.9,"to":"A. Keita"},{"n":"E. Frimpong","p":1,"min":1,"dir":"sr","rng":"s","dist":7.3,"out":"s","third":"m","tthird":"m","gs":"d","pos":"LM","press":"lp","xp":0.851,"xt":0.0011,"byp":-1,"phase":"ch","ch":"wl","x":-2.1,"y":19.9,"xe":-5.9,"ye":13.7,"to":"Germ\u00e1n Novoa"},{"n":"Germ\u00e1n Novoa","p":1,"min":1,"tdir":"sr","out":"u","third":"m","flb":1,"slb":1,"ahead":1,"gs":"d","pos":"RCB","press":"lp","xp":0.885,"xt":0.0048,"byp":7,"phase":"ch","ch":"hl","x":-6.3,"y":12.2,"xe":12.8,"ye":11.8,"to":"P. Ferrer"},{"n":"Andoni L\u00f3pez","p":1,"min":2,"dir":"sr","rng":"s","dist":7.0,"out":"s","third":"m","tthird":"a","one":1,"ahead":1,"gs":"d","pos":"LB","press":"hp","xp":0.869,"xt":0.0045,"byp":1,"phase":"fi","ch":"wl","x":13.8,"y":23.5,"xe":18.5,"ye":18.3,"to":"Vicente Esquerdo"},{"n":"Vicente Esquerdo","p":1,"min":2,"dir":"b","rng":"m","dist":21.2,"out":"s","third":"a","tthird":"m","one":1,"gs":"d","pos":"CM","press":"mp","xp":0.98,"xt":0.0008,"byp":-3,"phase":"fi","ch":"hl","x":18.5,"y":18.3,"xe":-1.7,"ye":11.7,"to":"Eneko Undabarrena"},{"n":"Eneko Undabarrena","p":1,"min":2,"dir":"sr","rng":"m","dist":24.9,"out":"s","third":"m","tthird":"m","gs":"d","pos":"LCB","press":"np","xp":1.0,"xt":0.0008,"byp":0,"phase":"cr","ch":"hl","x":-2.7,"y":9.9,"xe":-1.8,"ye":-14.9,"to":"Koke"},{"n":"Koke","p":1,"min":2,"dir":"f","rng":"m","dist":22.0,"out":"s","third":"m","tthird":"a","slb":1,"ahead":1,"gs":"d","pos":"RB","press":"np","xp":0.943,"xt":0.0023,"byp":6,"phase":"cr","ch":"hr","x":-0.4,"y":-18.1,"xe":21.6,"ye":-17.2,"to":"A. Keita"},{"n":"E. Frimpong","p":1,"min":3,"dir":"sr","rng":"s","dist":9.5,"out":"s","third":"a","tthird":"a","one":1,"gs":"d","pos":"LM","press":"lp","xp":0.988,"xt":0.0042,"byp":0,"phase":"fi","ch":"hr","x":20.1,"y":-17.0,"xe":20.1,"ye":-26.5,"to":"Koke"},{"n":"Koke","p":1,"min":3,"tdir":"f","out":"u","third":"a","slb":1,"ahead":1,"gs":"d","pos":"RB","press":"lp","xp":0.694,"xt":0.0068,"byp":2,"phase":"fi","ch":"wr","x":24.1,"y":-25.0,"xe":31.4,"ye":-21.9,"to":"A. Keita"},{"n":"Carlos Calder\u00f3n","p":1,"min":3,"dir":"b","rng":"m","dist":23.6,"out":"s","third":"a","tthird":"m","gs":"d","pos":"RF","press":"mp","xp":0.998,"xt":0.0003,"byp":-1,"phase":"fi","ch":"wr","x":18.7,"y":-29.7,"xe":-1.2,"ye":-17.1,"to":"Eneko Undabarrena"},{"n":"Eneko Undabarrena","p":1,"min":3,"dir":"sl","rng":"m","dist":25.7,"out":"s","third":"m","tthird":"m","gs":"d","pos":"LCB","press":"np","xp":0.997,"xt":0.0008,"byp":0,"phase":"cr","ch":"hr","x":-2.8,"y":-10.7,"xe":0.6,"ye":14.8,"to":"Germ\u00e1n Novoa"},{"n":"Germ\u00e1n Novoa","p":1,"min":3,"dir":"f","rng":"s","dist":11.7,"out":"s","third":"m","tthird":"m","flb":1,"ahead":1,"gs":"d","pos":"RCB","press":"lp","xp":0.811,"xt":0.0034,"byp":3,"phase":"cr","ch":"hl","x":3.6,"y":12.6,"xe":12.7,"ye":20.0,"to":"Borja V\u00e1zquez"},{"n":"Eneko Undabarrena","p":1,"min":3,"dir":"sl","rng":"m","dist":17.1,"out":"s","third":"m","tthird":"m","ahead":1,"gs":"d","pos":"LCB","press":"lp","xp":0.921,"xt":0.0049,"byp":1,"phase":"cr","ch":"hl","x":6.7,"y":6.8,"xe":14.9,"ye":21.9,"to":"Borja V\u00e1zquez"},{"n":"Borja V\u00e1zquez","p":1,"min":3,"dir":"f","rng":"s","dist":8.4,"out":"s","third":"m","tthird":"a","ahead":1,"gs":"d","pos":"RM","press":"mp","xp":0.959,"xt":0.0064,"byp":2,"phase":"fi","ch":"wl","x":18.0,"y":22.8,"xe":25.6,"ye":26.4,"to":"A. Keita"},{"n":"E. Frimpong","p":1,"min":4,"dir":"f","rng":"s","dist":9.8,"out":"s","third":"m","tthird":"m","slb":1,"ahead":1,"gs":"d","pos":"LM","press":"mp","xp":0.861,"xt":0.0058,"byp":2,"phase":"ch","ch":"c","x":1.5,"y":-10.4,"xe":11.3,"ye":-11.0,"to":"P. Ferrer"},{"n":"P. Ferrer","p":1,"min":4,"tdir":"sl","out":"u","third":"m","one":1,"gs":"d","pos":"CF","press":"hp","xp":0.914,"xt":0.004,"byp":-2,"phase":"ch","ch":"hr","x":11.3,"y":-11.0,"xe":3.4,"ye":-9.2,"to":"Vicente Esquerdo"},{"n":"Eneko Undabarrena","p":1,"min":4,"tdir":"b","out":"u","third":"d","ahead":1,"diff":1,"gs":"d","pos":"LCB","press":"mp","xp":0.525,"xt":0.0019,"byp":8,"phase":"ch","ch":"hr","x":-43.8,"y":-4.8,"xe":-5.4,"ye":-4.7,"to":"A. Keita"},{"n":"Andoni L\u00f3pez","p":1,"min":4,"dir":"sr","rng":"s","dist":9.2,"out":"s","third":"d","tthird":"d","gs":"d","pos":"LB","press":"np","xp":0.999,"xt":0.0004,"byp":-1,"phase":"bu","ch":"wl","x":-21.1,"y":30.5,"xe":-23.3,"ye":21.6,"to":"E. Frimpong"},{"n":"E. Frimpong","p":1,"min":4,"dir":"sr","rng":"s","dist":12.1,"out":"s","third":"d","tthird":"m","flb":1,"ahead":1,"gs":"d","pos":"LM","press":"np","xp":0.999,"xt":0.0007,"byp":0,"phase":"bu","ch":"wl","x":-23.1,"y":19.7,"xe":-16.6,"ye":9.4,"to":"Vicente Esquerdo"},{"n":"Vicente Esquerdo","p":1,"min":4,"dir":"sl","rng":"s","dist":7.8,"out":"s","third":"m","tthird":"d","one":1,"gs":"d","pos":"CM","press":"lp","xp":0.995,"xt":0.0003,"byp":-1,"phase":"cr","ch":"hl","x":-16.6,"y":9.4,"xe":-20.9,"ye":15.9,"to":"E. Frimpong"},{"n":"E. Frimpong","p":1,"min":4,"dir":"sr","rng":"s","dist":13.2,"out":"s","third":"d","tthird":"d","gs":"d","pos":"LM","press":"np","xp":0.999,"xt":0.0002,"byp":0,"phase":"cr","ch":"hl","x":-17.2,"y":3.3,"xe":-23.6,"ye":-8.3,"to":"Eneko Undabarrena"},{"n":"Eneko Undabarrena","p":1,"min":4,"dir":"sr","rng":"m","dist":27.0,"out":"s","third":"d","tthird":"m","ahead":1,"gs":"d","pos":"LCB","press":"np","xp":0.992,"xt":0.0005,"byp":3,"phase":"cr","ch":"c","x":-22.3,"y":-9.9,"xe":-4.1,"ye":-29.9,"to":"Koke"},{"n":"Koke","p":1,"min":4,"dir":"sl","rng":"s","dist":8.5,"out":"s","third":"m","tthird":"m","gs":"d","pos":"RB","press":"lp","xp":0.993,"xt":0.0009,"byp":-1,"phase":"cr","ch":"wr","x":-0.5,"y":-28.6,"xe":-1.6,"ye":-20.2,"to":"Vicente Esquerdo"},{"n":"Vicente Esquerdo","p":1,"min":4,"dir":"sl","rng":"l","dist":30.6,"out":"s","third":"m","tthird":"m","gs":"d","pos":"CM","press":"lp","xp":0.996,"xt":0.0001,"byp":0,"phase":"cr","ch":"wr","x":-3.2,"y":-19.9,"xe":-12.9,"ye":9.1,"to":"Germ\u00e1n Novoa"},{"n":"Germ\u00e1n Novoa","p":1,"min":5,"dir":"sl","rng":"m","dist":24.3,"out":"s","third":"m","tthird":"m","ahead":1,"gs":"d","pos":"RCB","press":"np","xp":0.995,"xt":0.001,"byp":1,"phase":"cr","ch":"c","x":-10.3,"y":12.9,"xe":3.5,"ye":32.9,"to":"Andoni L\u00f3pez"},{"n":"Andoni L\u00f3pez","p":1,"min":5,"dir":"b","rng":"m","dist":15.4,"out":"s","third":"m","tthird":"m","gs":"d","pos":"LB","press":"np","xp":0.999,"xt":0.0004,"byp":-2,"phase":"cr","ch":"wl","x":8.2,"y":31.4,"xe":-4.5,"ye":22.6,"to":"Germ\u00e1n Novoa"},{"n":"Germ\u00e1n Novoa","p":1,"min":5,"dir":"sl","rng":"m","dist":15.2,"out":"s","third":"m","tthird":"m","ahead":1,"gs":"d","pos":"RCB","press":"np","xp":0.994,"xt":0.0009,"byp":2,"phase":"cr","ch":"wl","x":1.1,"y":19.2,"xe":8.4,"ye":32.6,"to":"Andoni L\u00f3pez"},{"n":"Andoni L\u00f3pez","p":1,"min":5,"dir":"sr","rng":"m","dist":15.1,"out":"s","third":"m","tthird":"m","one":1,"gs":"d","pos":"LB","press":"np","xp":0.999,"xt":0.0009,"byp":-2,"phase":"cr","ch":"wl","x":8.4,"y":32.6,"xe":-0.1,"ye":20.1,"to":"Germ\u00e1n Novoa"},{"n":"Germ\u00e1n Novoa","p":1,"min":5,"dir":"sr","rng":"m","dist":17.2,"out":"s","third":"m","tthird":"m","gs":"d","pos":"RCB","press":"np","xp":0.999,"xt":0.0007,"byp":0,"phase":"cr","ch":"hl","x":0.0,"y":18.0,"xe":-6.3,"ye":2.0,"to":"Eneko Undabarrena"},{"n":"Eneko Undabarrena","p":1,"min":5,"dir":"sr","rng":"m","dist":26.2,"out":"s","third":"m","tthird":"m","ahead":1,"gs":"d","pos":"LCB","press":"np","xp":0.991,"xt":0.0018,"byp":1,"phase":"cr","ch":"c","x":-5.5,"y":-0.4,"xe":3.7,"ye":-25.0,"to":"Koke"},{"n":"Koke","p":1,"min":5,"dir":"f","rng":"s","dist":12.0,"out":"s","third":"m","tthird":"a","ahead":1,"gs":"d","pos":"RB","press":"np","xp":0.977,"xt":0.0025,"byp":4,"phase":"cr","ch":"wr","x":7.4,"y":-28.4,"xe":17.9,"ye":-34.2,"to":"Carlos Calder\u00f3n"},{"n":"A. Keita","p":1,"min":5,"dir":"sl","rng":"l","dist":44.5,"out":"s","third":"m","tthird":"m","high":1,"gs":"d","pos":"LF","press":"mp","xp":0.955,"xt":0.0029,"byp":0,"phase":"cr","ch":"wr","x":8.4,"y":-19.8,"xe":9.1,"ye":24.7,"to":"Andoni L\u00f3pez"},{"n":"Andoni L\u00f3pez","p":1,"min":5,"dir":"sr","rng":"m","dist":23.4,"out":"s","third":"m","tthird":"a","high":1,"dng":1,"ahead":1,"diff":1,"box":1,"gs":"d","pos":"LB","xp":0.403,"xt":0.0498,"byp":5,"phase":"fi","ch":"wl","x":22.0,"y":20.5,"xe":36.6,"ye":2.2,"to":"P. Ferrer"},{"n":"P. Ferrer","p":1,"min":6,"tdir":"sl","out":"u","third":"a","gs":"d","pos":"CF","press":"mp","xp":0.857,"xt":0.0082,"byp":-2,"phase":"ch","ch":"hl","x":33.9,"y":23.3,"xe":27.2,"ye":24.2,"to":"Andoni L\u00f3pez"},{"n":"Germ\u00e1n Novoa","p":1,"min":6,"dir":"f","rng":"s","dist":9.3,"out":"s","third":"m","tthird":"m","one":1,"ahead":1,"gs":"d","pos":"RCB","press":"mp","xp":0.938,"xt":0.0013,"byp":1,"phase":"cr","ch":"hl","x":-1.5,"y":17.0,"xe":7.6,"ye":19.4,"to":"E. Frimpong"},{"n":"E. Frimpong","p":1,"min":6,"dir":"sr","rng":"s","dist":12.3,"out":"s","third":"m","tthird":"m","gs":"d","pos":"LM","press":"lp","xp":0.997,"xt":0.0027,"byp":-1,"phase":"cr","ch":"hl","x":5.6,"y":20.7,"xe":4.5,"ye":8.5,"to":"Vicente Esquerdo"},{"n":"Vicente Esquerdo","p":1,"min":6,"dir":"sl","rng":"m","dist":20.1,"out":"s","third":"m","tthird":"m","gs":"d","pos":"CM","press":"np","xp":0.995,"xt":0.0012,"byp":0,"phase":"cr","ch":"c","x":9.0,"y":11.1,"xe":9.4,"ye":31.2,"to":"Andoni L\u00f3pez"},{"n":"Andoni L\u00f3pez","p":1,"min":6,"dir":"b","rng":"s","dist":14.3,"out":"s","third":"m","tthird":"m","gs":"d","pos":"LB","press":"np","xp":0.997,"xt":0.0006,"byp":-1,"phase":"fi","ch":"wl","x":9.8,"y":30.5,"xe":-3.2,"ye":24.5,"to":"Germ\u00e1n Novoa"},{"n":"Germ\u00e1n Novoa","p":1,"min":6,"dir":"sr","rng":"m","dist":23.5,"out":"s","third":"m","tthird":"m","gs":"d","pos":"RCB","press":"np","xp":0.999,"xt":0.0008,"byp":0,"phase":"cr","ch":"wl","x":-2.9,"y":23.0,"xe":-7.1,"ye":-0.1,"to":"Eneko Undabarrena"},{"n":"Eneko Undabarrena","p":1,"min":6,"dir":"sr","rng":"m","dist":24.1,"out":"s","third":"m","tthird":"m","ahead":1,"gs":"d","pos":"LCB","press":"np","xp":0.998,"xt":0.0014,"byp":1,"phase":"cr","ch":"c","x":-5.8,"y":-4.0,"xe":5.2,"ye":-25.5,"to":"Koke"},{"n":"Koke","p":1,"min":6,"dir":"b","rng":"m","dist":22.5,"out":"s","third":"m","tthird":"m","gs":"d","pos":"RB","press":"np","xp":0.999,"xt":0.0002,"byp":-1,"phase":"cr","ch":"wr","x":8.9,"y":-28.2,"xe":-10.6,"ye":-17.0,"to":"Eneko Undabarrena"},{"n":"Eneko Undabarrena","p":1,"min":6,"dir":"sl","rng":"l","dist":30.5,"out":"s","third":"m","tthird":"m","ahead":1,"gs":"d","pos":"LCB","press":"np","xp":0.997,"xt":0.0002,"byp":0,"phase":"cr","ch":"hr","x":-10.1,"y":-15.2,"xe":-3.4,"ye":14.6,"to":"Germ\u00e1n Novoa"},{"n":"Germ\u00e1n Novoa","p":1,"min":6,"dir":"f","rng":"m","dist":15.2,"out":"s","third":"m","tthird":"a","ahead":1,"gs":"d","pos":"RCB","press":"np","xp":0.966,"xt":0.0056,"byp":3,"phase":"cr","ch":"hl","x":4.7,"y":17.5,"xe":18.1,"ye":10.4,"to":"Borja V\u00e1zquez"},{"n":"Germ\u00e1n Novoa","p":1,"min":6,"dir":"sr","rng":"s","dist":11.0,"out":"s","third":"m","tthird":"m","gs":"d","pos":"RCB","press":"lp","xp":0.995,"xt":0.003,"byp":0,"phase":"fi","ch":"hl","x":12.0,"y":15.5,"xe":10.4,"ye":4.7,"to":"Vicente Esquerdo"},{"n":"Vicente Esquerdo","p":1,"min":6,"tdir":"sr","out":"u","third":"m","ahead":1,"gs":"d","pos":"CM","press":"np","xp":0.763,"xt":0.0068,"byp":7,"phase":"fi","ch":"c","x":10.7,"y":3.5,"xe":26.8,"ye":-31.6,"to":"Carlos Calder\u00f3n"},{"n":"Eneko Undabarrena","p":1,"min":6,"dir":"b","rng":"m","dist":24.2,"out":"s","third":"m","tthird":"d","gs":"d","pos":"LCB","press":"np","xp":0.999,"byp":0,"phase":"cr","ch":"wr","x":-21.9,"y":-17.4,"xe":-40.8,"ye":-2.3,"to":"Andr\u00e9s Prieto"},{"n":"Andr\u00e9s Prieto","p":1,"min":7,"dir":"f","rng":"m","dist":24.0,"out":"s","third":"d","tthird":"d","ahead":1,"gs":"d","pos":"GK","xp":0.991,"byp":0,"phase":"cr","ch":"c","x":-41.4,"y":-0.1,"xe":-22.8,"ye":-15.2,"to":"Eneko Undabarrena"},{"n":"Eneko Undabarrena","p":1,"min":7,"tdir":"f","out":"u","third":"d","flb":1,"llb":1,"slb":1,"ahead":1,"diff":1,"gs":"d","pos":"LCB","press":"np","xp":0.439,"xt":0.0032,"byp":7,"phase":"cr","ch":"hr","x":-17.0,"y":-20.6,"xe":11.3,"ye":-32.5,"to":"Carlos Calder\u00f3n"},{"n":"Carlos Calder\u00f3n","p":1,"min":7,"dir":"f","rng":"m","dist":22.7,"out":"s","third":"m","tthird":"a","shot":1,"ahead":1,"diff":1,"gs":"d","pos":"RF","press":"mp","xp":0.608,"xt":0.0061,"byp":4,"phase":"qb","ch":"c","x":3.2,"y":-9.3,"xe":25.8,"ye":-11.3,"to":"A. Keita"},{"n":"Koke","p":1,"min":9,"tdir":"b","out":"u","third":"d","ahead":1,"diff":1,"gs":"d","pos":"RB","press":"mp","xp":0.475,"xt":0.0004,"byp":8,"phase":"ch","ch":"wr","x":-49.6,"y":-31.6,"xe":-23.4,"ye":-10.5,"to":"A. Keita"},{"n":"Eneko Undabarrena","p":1,"min":9,"dir":"f","rng":"l","dist":31.9,"out":"s","third":"d","tthird":"m","high":1,"one":1,"ahead":1,"diff":1,"gs":"d","pos":"LCB","press":"hp","xp":0.534,"xt":0.0009,"byp":4,"phase":"ch","ch":"wr","x":-39.1,"y":-27.5,"xe":-12.0,"ye":-10.6,"to":"Borja V\u00e1zquez"},{"n":"Germ\u00e1n Novoa","p":1,"min":10,"dir":"f","rng":"l","dist":34.7,"out":"s","third":"d","tthird":"m","flb":1,"slb":1,"high":1,"ahead":1,"diff":1,"gs":"d","pos":"RCB","press":"lp","xp":0.506,"xt":0.0028,"byp":7,"phase":"di","ch":"hr","x":-19.3,"y":-13.2,"xe":15.3,"ye":-15.2,"to":"P. Ferrer"},{"n":"Borja V\u00e1zquez","p":1,"min":11,"dir":"sl","rng":"m","dist":21.4,"out":"s","third":"m","tthird":"m","gs":"d","pos":"RM","press":"hp","xp":0.991,"xt":0.0031,"byp":-3,"phase":"cr","ch":"hr","x":15.7,"y":-6.7,"xe":1.0,"ye":8.9,"to":"Andoni L\u00f3pez"},{"n":"Andoni L\u00f3pez","p":1,"min":11,"dir":"sl","rng":"s","dist":13.0,"out":"s","third":"m","tthird":"a","ahead":1,"gs":"d","pos":"LB","press":"np","xp":0.976,"xt":0.003,"byp":2,"phase":"fi","ch":"c","x":10.3,"y":21.0,"xe":19.2,"ye":30.5,"to":"Borja V\u00e1zquez"},{"n":"Borja V\u00e1zquez","p":1,"min":11,"dir":"b","rng":"s","dist":12.3,"out":"s","third":"a","tthird":"m","gs":"d","pos":"RM","press":"lp","xp":0.998,"xt":0.0018,"byp":-4,"phase":"fi","ch":"wl","x":24.0,"y":32.1,"xe":11.7,"ye":31.8,"to":"Andoni L\u00f3pez"},{"n":"Andoni L\u00f3pez","p":1,"min":11,"dir":"sr","rng":"l","dist":36.7,"out":"s","third":"m","tthird":"m","gs":"d","pos":"LB","press":"np","xp":0.998,"xt":0.0007,"byp":0,"phase":"fi","ch":"wl","x":10.7,"y":30.9,"xe":-1.8,"ye":-3.6,"to":"Eneko Undabarrena"},{"n":"Eneko Undabarrena","p":1,"min":11,"dir":"sr","rng":"m","dist":23.3,"out":"s","third":"m","tthird":"m","ahead":1,"gs":"d","pos":"LCB","press":"np","xp":0.996,"xt":0.0022,"byp":1,"phase":"cr","ch":"c","x":-0.3,"y":-6.2,"xe":10.3,"ye":-27.0,"to":"Koke"},{"n":"Koke","p":1,"min":11,"dir":"sr","rng":"s","dist":8.2,"out":"s","third":"m","tthird":"m","ahead":1,"gs":"d","pos":"RB","press":"np","xp":0.987,"xt":0.0014,"byp":1,"phase":"fi","ch":"wr","x":11.2,"y":-27.7,"xe":16.5,"ye":-33.9,"to":"Carlos Calder\u00f3n"},{"n":"Carlos Calder\u00f3n","p":1,"min":11,"dir":"f","rng":"s","dist":7.2,"out":"s","third":"m","tthird":"a","flb":1,"ahead":1,"gs":"d","pos":"RF","press":"lp","xp":0.957,"xt":0.0017,"byp":2,"phase":"fi","ch":"wr","x":19.1,"y":-31.4,"xe":26.3,"ye":-31.4,"to":"A. Keita"},{"n":"A. Keita","p":1,"min":11,"dir":"sl","rng":"s","dist":4.9,"out":"s","third":"a","tthird":"a","diff":1,"gs":"d","pos":"LF","press":"hp","xp":0.58,"xt":0.0121,"byp":2,"phase":"fi","ch":"wr","x":26.3,"y":-31.6,"xe":29.0,"ye":-27.5,"to":"Carlos Calder\u00f3n"},{"n":"Carlos Calder\u00f3n","p":1,"min":11,"tdir":"f","out":"u","third":"a","dng":1,"diff":1,"gs":"d","pos":"RF","press":"vhp","xp":0.212,"xt":0.1057,"byp":0,"phase":"fi","ch":"wr","x":42.2,"y":-26.6,"xe":41.3,"ye":-3.4,"to":"P. Ferrer"},{"n":"Vicente Esquerdo","p":1,"min":12,"dir":"sl","rng":"m","dist":29.8,"out":"s","third":"m","tthird":"m","gs":"d","pos":"CM","xp":0.988,"xt":0.0006,"byp":-1,"phase":"cr","ch":"wr","x":0.3,"y":-20.6,"xe":-6.5,"ye":8.5,"to":"Andoni L\u00f3pez"},{"n":"Andoni L\u00f3pez","p":1,"min":12,"dir":"b","rng":"m","dist":15.3,"out":"s","third":"m","tthird":"m","gs":"d","pos":"LB","press":"np","xp":0.999,"xt":0.0012,"byp":-2,"phase":"fi","ch":"c","x":10.4,"y":25.4,"xe":-2.0,"ye":16.4,"to":"Germ\u00e1n Novoa"},{"n":"Germ\u00e1n Novoa","p":1,"min":12,"dir":"sr","rng":"m","dist":17.1,"out":"s","third":"m","tthird":"m","gs":"d","pos":"RCB","press":"np","xp":1.0,"xt":0.0009,"byp":0,"phase":"cr","ch":"hl","x":-2.0,"y":14.8,"xe":-4.6,"ye":-2.1,"to":"Eneko Undabarrena"},{"n":"Eneko Undabarrena","p":1,"min":12,"dir":"sr","rng":"m","dist":26.8,"out":"s","third":"m","tthird":"a","ahead":1,"gs":"d","pos":"LCB","press":"np","xp":0.987,"xt":0.0025,"byp":4,"phase":"cr","ch":"c","x":4.9,"y":-11.6,"xe":20.0,"ye":-33.7,"to":"Carlos Calder\u00f3n"},{"n":"Carlos Calder\u00f3n","p":1,"min":12,"dir":"b","rng":"m","dist":19.4,"out":"s","third":"a","tthird":"m","gs":"d","pos":"RF","press":"lp","xp":0.965,"xt":0.0017,"byp":-2,"phase":"fi","ch":"wr","x":28.1,"y":-26.3,"xe":10.7,"ye":-17.6,"to":"Eneko Undabarrena"},{"n":"Eneko Undabarrena","p":1,"min":12,"dir":"sl","rng":"m","dist":20.3,"out":"s","third":"m","tthird":"m","one":1,"gs":"d","pos":"LCB","press":"np","xp":0.998,"xt":0.0017,"byp":0,"phase":"fi","ch":"hr","x":10.7,"y":-17.6,"xe":5.3,"ye":1.9,"to":"Germ\u00e1n Novoa"},{"n":"Germ\u00e1n Novoa","p":1,"min":12,"dir":"sr","rng":"s","dist":14.3,"out":"s","third":"m","tthird":"m","ahead":1,"gs":"d","pos":"RCB","press":"np","xp":0.997,"xt":0.0028,"byp":0,"phase":"fi","ch":"c","x":7.6,"y":5.4,"xe":12.5,"ye":-8.0,"to":"Vicente Esquerdo"},{"n":"Vicente Esquerdo","p":1,"min":12,"dir":"sl","rng":"m","dist":16.6,"out":"s","third":"m","tthird":"m","gs":"d","pos":"CM","press":"lp","xp":0.993,"xt":0.002,"byp":0,"phase":"fi","ch":"c","x":12.6,"y":-7.2,"xe":5.9,"ye":8.0,"to":"Germ\u00e1n Novoa"},{"n":"Germ\u00e1n Novoa","p":1,"min":12,"dir":"sl","rng":"m","dist":18.4,"out":"s","third":"m","tthird":"m","ahead":1,"gs":"d","pos":"RCB","press":"np","xp":0.98,"xt":0.0016,"byp":0,"phase":"fi","ch":"c","x":7.2,"y":11.5,"xe":12.3,"ye":29.2,"to":"Andoni L\u00f3pez"},{"n":"Andoni L\u00f3pez","p":1,"min":12,"dir":"sr","rng":"s","dist":13.2,"out":"s","third":"m","tthird":"m","gs":"d","pos":"LB","press":"np","xp":0.999,"xt":0.0015,"byp":0,"phase":"fi","ch":"wl","x":11.9,"y":28.4,"xe":5.1,"ye":17.2,"to":"Germ\u00e1n Novoa"},{"n":"Germ\u00e1n Novoa","p":1,"min":12,"dir":"sr","rng":"m","dist":16.9,"out":"s","third":"m","tthird":"m","gs":"d","pos":"RCB","xp":0.999,"xt":0.002,"byp":0,"phase":"fi","ch":"hl","x":4.9,"y":16.8,"xe":5.4,"ye":-0.1,"to":"Vicente Esquerdo"},{"n":"Vicente Esquerdo","p":1,"min":12,"dir":"f","rng":"m","dist":18.5,"out":"s","third":"m","tthird":"a","flb":1,"slb":1,"ahead":1,"gs":"d","pos":"CM","press":"np","xp":0.659,"xt":0.0153,"byp":6,"phase":"cr","ch":"c","x":6.6,"y":-1.0,"xe":21.7,"ye":9.6,"to":"E. Frimpong"},{"n":"E. Frimpong","p":1,"min":12,"dir":"b","rng":"m","dist":15.2,"out":"s","third":"a","tthird":"m","diff":1,"gs":"d","pos":"LM","press":"hp","xp":0.356,"xt":0.0016,"byp":-4,"phase":"cr","ch":"hl","x":17.5,"y":8.1,"xe":3.9,"ye":15.1,"to":"Germ\u00e1n Novoa"},{"n":"Germ\u00e1n Novoa","p":1,"min":12,"dir":"f","rng":"m","dist":22.1,"out":"s","third":"m","tthird":"a","ahead":1,"gs":"d","pos":"RCB","press":"np","xp":0.99,"xt":0.0021,"byp":3,"phase":"cr","ch":"hl","x":4.2,"y":17.0,"xe":20.3,"ye":32.2,"to":"Borja V\u00e1zquez"},{"n":"Borja V\u00e1zquez","p":1,"min":12,"dir":"f","rng":"m","dist":15.2,"out":"s","third":"a","tthird":"a","llb":1,"slb":1,"one":1,"ahead":1,"diff":1,"gs":"d","pos":"RM","press":"lp","xp":0.619,"xt":0.0163,"byp":6,"phase":"fi","ch":"wl","x":20.3,"y":32.2,"xe":32.6,"ye":23.1,"to":"Andoni L\u00f3pez"},{"n":"Carlos Calder\u00f3n","p":1,"min":14,"dir":"sl","rng":"s","dist":8.4,"out":"s","third":"m","tthird":"m","gs":"d","pos":"RF","press":"lp","xp":0.977,"xt":0.0023,"byp":0,"phase":"cr","ch":"wr","x":13.6,"y":-22.7,"xe":10.9,"ye":-14.7,"to":"E. Frimpong"},{"n":"E. Frimpong","p":1,"min":14,"dir":"sr","rng":"s","dist":11.4,"out":"s","third":"m","tthird":"m","one":1,"gs":"d","pos":"LM","press":"mp","xp":0.981,"xt":0.0018,"byp":-1,"phase":"cr","ch":"hr","x":10.9,"y":-14.7,"xe":8.2,"ye":-25.8,"to":"Koke"},{"n":"Koke","p":1,"min":14,"dir":"sl","rng":"s","dist":7.6,"out":"s","third":"m","tthird":"m","gs":"d","pos":"RB","press":"lp","xp":0.998,"xt":0.0008,"byp":0,"phase":"cr","ch":"wr","x":8.5,"y":-26.9,"xe":6.3,"ye":-19.6,"to":"E. Frimpong"},{"n":"E. Frimpong","p":1,"min":14,"dir":"sr","rng":"s","dist":8.0,"out":"s","third":"m","tthird":"m","gs":"d","pos":"LM","press":"np","xp":0.994,"xt":0.0006,"byp":-1,"phase":"cr","ch":"hr","x":6.6,"y":-19.9,"xe":6.1,"ye":-27.9,"to":"Koke"},{"n":"Koke","p":1,"min":14,"dir":"sl","rng":"m","dist":22.1,"out":"s","third":"m","tthird":"m","one":1,"gs":"d","pos":"RB","press":"np","xp":0.998,"xt":0.0003,"byp":0,"phase":"cr","ch":"wr","x":6.1,"y":-27.9,"xe":-5.0,"ye":-8.8,"to":"Eneko Undabarrena"},{"n":"Eneko Undabarrena","p":1,"min":14,"dir":"sl","rng":"l","dist":33.7,"out":"s","third":"m","tthird":"m","ahead":1,"gs":"d","pos":"LCB","press":"np","xp":0.91,"xt":0.002,"byp":1,"phase":"cr","ch":"c","x":-0.6,"y":2.3,"xe":9.5,"ye":34.5,"to":"Andoni L\u00f3pez"},{"n":"Andoni L\u00f3pez","p":1,"min":14,"dir":"sr","rng":"m","dist":16.1,"out":"s","third":"m","tthird":"m","gs":"d","pos":"LB","press":"np","xp":0.999,"xt":0.0012,"byp":-1,"phase":"fi","ch":"wl","x":12.2,"y":34.9,"xe":2.2,"ye":22.3,"to":"Germ\u00e1n Novoa"},{"n":"Germ\u00e1n Novoa","p":1,"min":14,"dir":"f","rng":"s","dist":9.5,"out":"s","third":"m","tthird":"m","flb":1,"ahead":1,"gs":"d","pos":"RCB","press":"np","xp":0.984,"xt":0.0038,"byp":2,"phase":"cr","ch":"wl","x":2.0,"y":22.8,"xe":10.7,"ye":19.1,"to":"Vicente Esquerdo"},{"n":"Vicente Esquerdo","p":1,"min":14,"dir":"sl","rng":"s","dist":13.4,"out":"s","third":"m","tthird":"m","one":1,"gs":"d","pos":"CM","press":"mp","xp":0.88,"xt":0.0014,"byp":0,"phase":"fi","ch":"hl","x":10.7,"y":19.1,"xe":10.4,"ye":32.5,"to":"Andoni L\u00f3pez"},{"n":"Andoni L\u00f3pez","p":1,"min":14,"dir":"f","rng":"m","dist":17.4,"out":"s","third":"m","tthird":"a","llb":1,"slb":1,"ahead":1,"diff":1,"gs":"d","pos":"LB","press":"np","xp":0.634,"xt":0.0091,"byp":5,"phase":"fi","ch":"wl","x":16.6,"y":33.2,"xe":33.9,"ye":30.8,"to":"Borja V\u00e1zquez"},{"n":"Germ\u00e1n Novoa","p":1,"min":14,"dir":"sr","rng":"m","dist":16.9,"out":"s","third":"m","tthird":"m","gs":"d","pos":"RCB","press":"mp","xp":0.995,"xt":0.0005,"byp":0,"phase":"cr","ch":"wl","x":-5.7,"y":29.9,"xe":-10.7,"ye":13.8,"to":"Eneko Undabarrena"},{"n":"Eneko Undabarrena","p":1,"min":14,"dir":"sr","rng":"m","dist":28.8,"out":"s","third":"m","tthird":"m","gs":"d","pos":"LCB","press":"np","xp":0.997,"xt":0.0012,"byp":0,"phase":"cr","ch":"hl","x":-8.1,"y":3.9,"xe":-1.5,"ye":-24.2,"to":"Koke"},{"n":"Koke","p":1,"min":15,"dir":"f","rng":"m","dist":16.4,"out":"s","third":"m","tthird":"m","slb":1,"ahead":1,"gs":"d","pos":"RB","press":"np","xp":0.943,"xt":0.0031,"byp":4,"phase":"cr","ch":"wr","x":0.4,"y":-25.3,"xe":15.9,"ye":-20.1,"to":"A. Keita"},{"n":"A. Keita","p":1,"min":15,"dir":"b","rng":"s","dist":12.1,"out":"s","third":"m","tthird":"m","gs":"d","pos":"LF","xp":0.956,"xt":0.0007,"byp":-4,"phase":"cr","ch":"hr","x":14.0,"y":-24.6,"xe":2.1,"ye":-27.0,"to":"Koke"},{"n":"Koke","p":1,"min":15,"dir":"sl","rng":"s","dist":9.1,"out":"s","third":"m","tthird":"m","gs":"d","pos":"RB","press":"np","xp":0.999,"xt":0.0004,"byp":0,"phase":"cr","ch":"wr","x":1.7,"y":-25.9,"xe":0.1,"ye":-16.9,"to":"E. Frimpong"},{"n":"E. Frimpong","p":1,"min":15,"dir":"sr","rng":"m","dist":18.6,"out":"s","third":"m","tthird":"m","ahead":1,"gs":"d","pos":"LM","press":"np","xp":0.987,"xt":0.0018,"byp":3,"phase":"cr","ch":"hr","x":1.7,"y":-13.2,"xe":11.3,"ye":-29.1,"to":"A. Keita"},{"n":"A. Keita","p":1,"min":15,"dir":"f","rng":"s","dist":12.0,"out":"s","third":"m","tthird":"a","flb":1,"slb":1,"shot":1,"ahead":1,"gs":"d","pos":"LF","press":"lp","xp":0.729,"xt":0.0142,"byp":4,"phase":"fi","ch":"wr","x":16.0,"y":-21.4,"xe":26.1,"ye":-15.1,"to":"Koke"},{"n":"Koke","p":1,"min":15,"dir":"b","rng":"s","dist":5.6,"out":"s","third":"a","tthird":"a","one":1,"shot":1,"gs":"d","pos":"RB","press":"hp","xp":0.697,"xt":0.0118,"byp":-3,"phase":"fi","ch":"hr","x":26.1,"y":-15.1,"xe":21.9,"ye":-11.5,"to":"A. Keita"},{"n":"A. Keita","p":1,"min":15,"dir":"sr","rng":"s","dist":9.1,"out":"s","third":"a","tthird":"a","slb":1,"high":1,"dng":1,"shot":1,"ahead":1,"diff":1,"gs":"d","pos":"LF","press":"mp","xp":0.434,"xt":0.0242,"byp":2,"phase":"fi","ch":"hr","x":28.2,"y":-3.8,"xe":33.8,"ye":-10.9,"to":"Koke"},{"n":"Koke","p":1,"min":15,"dir":"sl","rng":"s","dist":12.4,"out":"s","third":"a","tthird":"a","shot":1,"gs":"d","pos":"RB","press":"hp","xp":0.89,"xt":0.0195,"byp":-2,"phase":"fi","ch":"hr","x":33.6,"y":-7.7,"xe":29.2,"ye":3.9,"to":"Borja V\u00e1zquez"},{"n":"Andoni L\u00f3pez","p":1,"min":16,"dir":"f","rng":"s","dist":10.7,"out":"s","third":"m","tthird":"m","shot":1,"ahead":1,"gs":"d","pos":"LB","xp":0.828,"xt":0.0021,"byp":3,"phase":"cr","ch":"wl","x":-15.7,"y":31.3,"xe":-5.7,"ye":27.3,"to":"Borja V\u00e1zquez"},{"n":"Carlos Calder\u00f3n","p":1,"min":17,"dir":"b","rng":"s","dist":13.7,"out":"s","third":"a","tthird":"a","gs":"d","pos":"RF","press":"lp","xp":0.982,"xt":0.0053,"byp":-3,"phase":"sp","ch":"wr","x":42.8,"y":-31.2,"xe":29.7,"ye":-27.1,"to":"Koke"},{"n":"Koke","p":1,"min":17,"dir":"f","rng":"s","dist":11.2,"out":"s","third":"a","tthird":"a","ahead":1,"gs":"d","pos":"RB","press":"mp","xp":0.866,"xt":0.0122,"byp":4,"phase":"sp","ch":"wr","x":32.0,"y":-27.2,"xe":43.1,"ye":-28.4,"to":"Andoni L\u00f3pez"},{"n":"Andoni L\u00f3pez","p":1,"min":17,"dir":"sl","rng":"m","dist":21.1,"out":"s","third":"a","tthird":"a","one":1,"diff":1,"box":1,"gs":"d","pos":"LB","press":"hp","xp":0.442,"xt":0.0174,"byp":0,"phase":"sp","ch":"wr","x":43.1,"y":-28.4,"xe":40.1,"ye":-7.5,"to":"A. Keita"},{"n":"E. Frimpong","p":1,"min":18,"dir":"b","rng":"s","dist":13.8,"out":"s","third":"m","tthird":"m","gs":"d","pos":"LM","xp":0.822,"xt":0.0007,"byp":-4,"phase":"cr","ch":"c","x":4.5,"y":-0.1,"xe":-5.5,"ye":-9.6,"to":"Eneko Undabarrena"},{"n":"Eneko Undabarrena","p":1,"min":18,"dir":"sr","rng":"s","dist":12.4,"out":"s","third":"m","tthird":"m","gs":"d","pos":"LCB","press":"lp","xp":0.996,"xt":0.0004,"byp":0,"phase":"cr","ch":"hr","x":-8.0,"y":-13.2,"xe":-10.9,"ye":-25.3,"to":"Koke"},{"n":"Koke","p":1,"min":18,"dir":"sl","rng":"l","dist":33.2,"out":"s","third":"m","tthird":"d","gs":"d","pos":"RB","press":"np","xp":0.998,"xt":0.0002,"byp":0,"phase":"cr","ch":"wr","x":-12.1,"y":-24.9,"xe":-21.4,"ye":7.0,"to":"Germ\u00e1n Novoa"},{"n":"Germ\u00e1n Novoa","p":1,"min":18,"dir":"sr","rng":"s","dist":13.4,"out":"s","third":"d","tthird":"m","gs":"d","pos":"RCB","press":"np","xp":0.999,"xt":0.0003,"byp":0,"phase":"cr","ch":"c","x":-17.7,"y":9.2,"xe":-16.1,"ye":-4.0,"to":"Eneko Undabarrena"},{"n":"Eneko Undabarrena","p":1,"min":18,"dir":"f","rng":"m","dist":22.4,"out":"s","third":"m","tthird":"m","flb":1,"slb":1,"ahead":1,"gs":"d","pos":"LCB","press":"lp","xp":0.952,"xt":0.002,"byp":5,"phase":"cr","ch":"c","x":-15.4,"y":-4.1,"xe":4.3,"ye":-14.9,"to":"P. Ferrer"},{"n":"P. Ferrer","p":1,"min":18,"dir":"sl","rng":"s","dist":11.7,"out":"s","third":"m","tthird":"m","one":1,"ahead":1,"gs":"d","pos":"CF","press":"hp","xp":0.793,"xt":0.007,"byp":2,"phase":"cr","ch":"hr","x":4.3,"y":-14.9,"xe":12.3,"ye":-6.3,"to":"A. Keita"},{"n":"A. Keita","p":1,"min":18,"dir":"b","rng":"s","dist":6.3,"out":"s","third":"m","tthird":"m","gs":"d","pos":"LF","press":"mp","xp":0.944,"xt":0.0042,"byp":-1,"phase":"cr","ch":"c","x":11.5,"y":-8.2,"xe":5.2,"ye":-7.2,"to":"Vicente Esquerdo"},{"n":"Vicente Esquerdo","p":1,"min":18,"dir":"sr","rng":"l","dist":31.1,"out":"s","third":"m","tthird":"a","slb":1,"ahead":1,"gs":"d","pos":"CM","press":"lp","xp":0.889,"xt":0.0073,"byp":2,"phase":"cr","ch":"c","x":7.7,"y":-6.8,"xe":27.9,"ye":-30.5,"to":"Carlos Calder\u00f3n"},{"n":"Carlos Calder\u00f3n","p":1,"min":18,"dir":"f","rng":"s","dist":4.5,"out":"s","third":"a","tthird":"a","llb":1,"ahead":1,"gs":"d","pos":"RF","press":"mp","xp":0.852,"xt":0.0166,"byp":2,"phase":"fi","ch":"wr","x":32.4,"y":-27.9,"xe":36.7,"ye":-29.3,"to":"Koke"},{"n":"Koke","p":1,"min":18,"tdir":"f","out":"u","third":"a","dng":1,"diff":1,"gs":"d","pos":"RB","press":"hp","xp":0.52,"xt":0.0607,"byp":-6,"phase":"fi","ch":"wr","x":46.5,"y":-23.5,"xe":38.8,"ye":-8.5,"to":"A. Keita"},{"n":"Vicente Esquerdo","p":1,"min":25,"dir":"b","rng":"s","dist":9.9,"out":"s","third":"a","tthird":"a","gs":"w","pos":"CM","press":"mp","xp":0.988,"xt":0.0037,"byp":-1,"phase":"sp","ch":"hr","x":35.5,"y":-21.2,"xe":25.7,"ye":-23.0,"to":"Koke"},{"n":"Koke","p":1,"min":25,"dir":"f","rng":"s","dist":10.1,"out":"s","third":"a","tthird":"a","one":1,"ahead":1,"gs":"w","pos":"RB","press":"np","xp":0.991,"xt":0.0038,"byp":1,"phase":"sp","ch":"wr","x":25.7,"y":-23.0,"xe":33.7,"ye":-29.2,"to":"Vicente Esquerdo"},{"n":"Vicente Esquerdo","p":1,"min":25,"dir":"sl","rng":"s","dist":10.9,"out":"s","third":"a","tthird":"a","ahead":1,"gs":"w","pos":"CM","press":"lp","xp":0.841,"xt":0.0076,"byp":1,"phase":"sp","ch":"wr","x":31.8,"y":-26.1,"xe":34.6,"ye":-15.6,"to":"A. Keita"},{"n":"E. Frimpong","p":1,"min":25,"dir":"sr","rng":"s","dist":9.2,"out":"s","third":"m","tthird":"m","one":1,"gs":"w","pos":"LM","press":"mp","phase":"cr","ch":"hr","x":16.0,"y":-10.0,"xe":16.0,"ye":-19.2,"to":"Borja V\u00e1zquez"},{"n":"Borja V\u00e1zquez","p":1,"min":25,"dir":"f","rng":"s","dist":10.6,"out":"s","third":"m","tthird":"a","shot":1,"ahead":1,"gs":"w","pos":"RM","press":"np","xp":0.791,"xt":0.0198,"byp":3,"phase":"fi","ch":"hr","x":27.1,"y":-23.3,"xe":37.5,"ye":-25.2,"to":"Carlos Calder\u00f3n"},{"n":"Carlos Calder\u00f3n","p":1,"min":25,"dir":"sl","rng":"m","dist":24.1,"out":"s","third":"a","tthird":"a","high":1,"dng":1,"shot":1,"diff":1,"box":1,"gs":"w","pos":"RF","press":"mp","xp":0.282,"xt":0.1326,"byp":-3,"phase":"fi","ch":"wr","x":50.3,"y":-20.6,"xe":46.5,"ye":3.2,"to":"P. Ferrer"},{"n":"E. Frimpong","p":1,"min":27,"dir":"sl","rng":"m","dist":27.1,"out":"s","third":"m","tthird":"m","ahead":1,"gs":"w","pos":"LM","press":"lp","xp":0.952,"xt":0.0044,"byp":2,"phase":"cr","ch":"hl","x":-5.3,"y":12.9,"xe":13.7,"ye":32.2,"to":"A. Keita"},{"n":"A. Keita","p":1,"min":28,"dir":"b","rng":"m","dist":15.2,"out":"s","third":"m","tthird":"m","gs":"w","pos":"LF","press":"lp","xp":0.964,"xt":0.0016,"byp":-2,"phase":"fi","ch":"wl","x":14.0,"y":32.3,"xe":2.9,"ye":21.9,"to":"E. Frimpong"},{"n":"Andoni L\u00f3pez","p":1,"min":28,"dir":"sr","rng":"s","dist":10.9,"out":"s","third":"m","tthird":"m","one":1,"gs":"w","pos":"LB","press":"np","xp":0.999,"xt":0.0009,"byp":0,"phase":"cr","ch":"wl","x":3.0,"y":32.2,"xe":-1.7,"ye":22.4,"to":"E. Frimpong"},{"n":"E. Frimpong","p":1,"min":28,"dir":"sr","rng":"s","dist":11.8,"out":"s","third":"m","tthird":"m","gs":"w","pos":"LM","press":"np","xp":0.998,"xt":0.0004,"byp":-1,"phase":"cr","ch":"wl","x":-2.8,"y":21.1,"xe":-11.0,"ye":12.6,"to":"Germ\u00e1n Novoa"},{"n":"Germ\u00e1n Novoa","p":1,"min":28,"dir":"sr","rng":"m","dist":25.0,"out":"s","third":"m","tthird":"m","flb":1,"ahead":1,"gs":"w","pos":"RCB","press":"np","xp":0.986,"xt":0.0021,"byp":3,"phase":"cr","ch":"hl","x":-10.6,"y":10.0,"xe":5.7,"ye":-9.0,"to":"P. Ferrer"},{"n":"P. Ferrer","p":1,"min":28,"dir":"sl","rng":"s","dist":6.7,"out":"s","third":"m","tthird":"m","one":1,"gs":"w","pos":"CF","press":"lp","xp":0.955,"xt":0.0029,"byp":-1,"phase":"cr","ch":"c","x":5.7,"y":-9.0,"xe":1.6,"ye":-3.6,"to":"Vicente Esquerdo"},{"n":"Vicente Esquerdo","p":1,"min":28,"dir":"sr","rng":"m","dist":22.6,"out":"s","third":"m","tthird":"m","one":1,"gs":"w","pos":"CM","press":"lp","xp":0.993,"xt":0.0022,"byp":1,"phase":"cr","ch":"c","x":1.6,"y":-3.6,"xe":5.1,"ye":-25.9,"to":"Koke"},{"n":"Koke","p":1,"min":28,"dir":"f","rng":"m","dist":15.2,"out":"s","third":"m","tthird":"a","ahead":1,"gs":"w","pos":"RB","press":"np","xp":0.982,"xt":0.0036,"byp":2,"phase":"cr","ch":"wr","x":9.1,"y":-24.9,"xe":21.5,"ye":-33.6,"to":"Carlos Calder\u00f3n"},{"n":"Carlos Calder\u00f3n","p":1,"min":28,"dir":"b","rng":"s","dist":10.1,"out":"s","third":"a","tthird":"m","one":1,"gs":"w","pos":"RF","press":"mp","xp":0.993,"xt":0.0014,"byp":-4,"phase":"fi","ch":"wr","x":21.5,"y":-33.6,"xe":13.1,"ye":-28.1,"to":"Koke"},{"n":"Koke","p":1,"min":28,"dir":"b","rng":"s","dist":9.6,"out":"s","third":"m","tthird":"m","gs":"w","pos":"RB","press":"lp","xp":0.997,"xt":0.0009,"byp":-1,"phase":"fi","ch":"wr","x":13.5,"y":-27.7,"xe":4.6,"ye":-24.1,"to":"Vicente Esquerdo"},{"n":"Vicente Esquerdo","p":1,"min":28,"dir":"sl","rng":"l","dist":36.7,"out":"s","third":"m","tthird":"m","gs":"w","pos":"CM","press":"np","xp":0.991,"xt":0.0004,"byp":0,"phase":"cr","ch":"wr","x":2.8,"y":-22.6,"xe":-7.3,"ye":12.7,"to":"Germ\u00e1n Novoa"},{"n":"Germ\u00e1n Novoa","p":1,"min":28,"dir":"sr","rng":"l","dist":35.1,"out":"s","third":"m","tthird":"m","high":1,"ahead":1,"gs":"w","pos":"RCB","press":"np","xp":0.992,"xt":0.0009,"byp":1,"phase":"cr","ch":"hl","x":-5.4,"y":11.3,"xe":-0.4,"ye":-23.4,"to":"Koke"},{"n":"Koke","p":1,"min":28,"tdir":"f","out":"u","third":"m","flb":1,"llb":1,"slb":1,"ahead":1,"diff":1,"gs":"w","pos":"RB","press":"np","xp":0.607,"xt":0.0121,"byp":7,"phase":"cr","ch":"wr","x":4.2,"y":-22.8,"xe":21.8,"ye":-9.3,"to":"P. Ferrer"},{"n":"E. Frimpong","p":1,"min":29,"dir":"b","rng":"m","dist":19.3,"out":"s","third":"d","tthird":"d","gs":"w","pos":"LM","press":"mp","xp":0.98,"byp":-4,"phase":"cr","ch":"c","x":-19.9,"y":30.0,"xe":-39.0,"ye":27.6,"to":"Andoni L\u00f3pez"},{"n":"Andoni L\u00f3pez","p":1,"min":29,"dir":"f","rng":"l","dist":55.2,"out":"s","third":"d","tthird":"a","flb":1,"llb":1,"slb":1,"high":1,"ahead":1,"diff":1,"gs":"w","pos":"LB","press":"np","xp":0.407,"xt":0.0071,"byp":10,"phase":"di","ch":"wl","x":-31.2,"y":26.6,"xe":23.6,"ye":20.5,"to":"A. Keita"},{"n":"Koke","p":1,"min":29,"dir":"sr","rng":"s","dist":12.7,"out":"s","third":"a","tthird":"a","shot":1,"gs":"w","pos":"RB","press":"mp","xp":0.972,"xt":0.012,"byp":3,"phase":"fi","ch":"hr","x":29.9,"y":-16.3,"xe":37.7,"ye":-26.2,"to":"Carlos Calder\u00f3n"},{"n":"Vicente Esquerdo","p":1,"min":38,"tdir":"b","out":"u","third":"m","one":1,"header":1,"diff":1,"gs":"w","pos":"CM","xp":0.534,"xt":0.0022,"byp":-1,"phase":"cr","ch":"hl","x":-1.6,"y":11.3,"xe":-5.3,"ye":16.9,"to":"Eneko Undabarrena"},{"n":"A. Keita","p":1,"min":39,"tdir":"b","out":"u","third":"m","one":1,"gs":"w","pos":"LF","press":"mp","phase":"ch","ch":"hl","x":5.0,"y":17.8,"xe":4.8,"ye":13.0,"to":"E. Frimpong"},{"n":"Vicente Esquerdo","p":1,"min":39,"dir":"sr","rng":"m","dist":20.0,"out":"s","third":"d","tthird":"d","ahead":1,"gs":"w","pos":"CM","press":"mp","xp":0.882,"xt":0.0047,"byp":1,"phase":"bu","ch":"hl","x":-25.9,"y":16.0,"xe":-19.9,"ye":-3.1,"to":"Borja V\u00e1zquez"},{"n":"Andr\u00e9s Prieto","p":1,"min":40,"dir":"f","rng":"l","dist":40.9,"out":"s","third":"d","tthird":"m","slb":1,"high":1,"ahead":1,"gs":"w","pos":"GK","xp":0.697,"xt":0.0014,"byp":5,"phase":"di","ch":"c","x":-40.3,"y":9.3,"xe":0.6,"ye":11.5,"to":"P. Ferrer"},{"n":"P. Ferrer","p":1,"min":40,"dir":"b","rng":"s","dist":8.2,"out":"s","third":"m","tthird":"m","gs":"w","pos":"CF","press":"vhp","xp":0.975,"xt":0.0022,"byp":-2,"phase":"cr","ch":"hl","x":-1.3,"y":9.3,"xe":-9.2,"ye":7.3,"to":"Vicente Esquerdo"},{"n":"Vicente Esquerdo","p":1,"min":40,"dir":"sr","rng":"m","dist":22.3,"out":"s","third":"m","tthird":"m","one":1,"ahead":1,"gs":"w","pos":"CM","press":"mp","xp":0.86,"xt":0.0109,"byp":5,"phase":"cr","ch":"c","x":-9.2,"y":7.3,"xe":5.0,"ye":-9.9,"to":"Borja V\u00e1zquez"},{"n":"E. Frimpong","p":1,"min":40,"dir":"f","rng":"m","dist":29.1,"out":"s","third":"d","tthird":"m","high":1,"ahead":1,"diff":1,"gs":"w","pos":"LM","press":"mp","xp":0.635,"xt":0.0031,"byp":6,"phase":"ch","ch":"hl","x":-39.0,"y":12.2,"xe":-10.4,"ye":6.8,"to":"A. Keita"},{"n":"E. Frimpong","p":1,"min":40,"dir":"f","rng":"s","dist":9.2,"out":"s","third":"d","tthird":"d","one":1,"ahead":1,"gs":"w","pos":"LM","press":"mp","xp":0.943,"xt":0.0012,"byp":1,"phase":"ch","ch":"hl","x":-29.1,"y":12.4,"xe":-21.0,"ye":8.1,"to":"Andoni L\u00f3pez"},{"n":"Carlos Calder\u00f3n","p":1,"min":41,"tdir":"f","out":"u","third":"a","dng":1,"diff":1,"gs":"w","pos":"RF","press":"hp","xp":0.249,"xt":0.0357,"byp":-5,"phase":"fi","ch":"wr","x":49.0,"y":-31.3,"xe":40.0,"ye":-11.3,"to":"A. Keita"},{"n":"E. Frimpong","p":1,"min":43,"dir":"sr","rng":"l","dist":45.5,"out":"s","third":"m","tthird":"m","high":1,"gs":"w","pos":"LM","press":"lp","xp":0.945,"xt":0.0015,"byp":-2,"phase":"cr","ch":"wl","x":-3.2,"y":28.5,"xe":-7.0,"ye":-16.8,"to":"Koke"},{"n":"Koke","p":1,"min":43,"dir":"sr","rng":"s","dist":11.2,"out":"s","third":"m","tthird":"a","gs":"w","pos":"RB","press":"np","xp":0.992,"xt":0.0059,"byp":0,"phase":"fi","ch":"hr","x":19.2,"y":-23.1,"xe":24.2,"ye":-33.1,"to":"Carlos Calder\u00f3n"},{"n":"Carlos Calder\u00f3n","p":1,"min":43,"tdir":"sl","out":"u","third":"a","ahead":1,"gs":"w","pos":"RF","press":"mp","xp":0.827,"xt":0.012,"byp":2,"phase":"fi","ch":"wr","x":28.9,"y":-25.5,"xe":34.8,"ye":-9.5,"to":"A. Keita"},{"n":"Carlos Calder\u00f3n","p":1,"min":43,"dir":"sr","rng":"m","dist":23.2,"out":"s","third":"a","tthird":"m","gs":"w","pos":"RF","press":"hp","xp":0.996,"xt":0.0018,"byp":-2,"phase":"fi","ch":"c","x":12.8,"y":3.0,"xe":0.1,"ye":-16.4,"to":"Koke"},{"n":"Koke","p":1,"min":43,"dir":"sl","rng":"m","dist":16.3,"out":"s","third":"m","tthird":"m","gs":"w","pos":"RB","press":"np","xp":0.999,"xt":0.0005,"byp":0,"phase":"cr","ch":"hr","x":0.1,"y":-16.1,"xe":-5.8,"ye":-1.0,"to":"Eneko Undabarrena"},{"n":"Eneko Undabarrena","p":1,"min":43,"dir":"sl","rng":"s","dist":10.7,"out":"s","third":"m","tthird":"m","ahead":1,"gs":"w","pos":"LCB","press":"np","xp":0.999,"xt":0.0006,"byp":0,"phase":"cr","ch":"c","x":-4.6,"y":0.4,"xe":-1.3,"ye":10.6,"to":"Germ\u00e1n Novoa"},{"n":"Germ\u00e1n Novoa","p":1,"min":43,"dir":"sr","rng":"s","dist":10.8,"out":"s","third":"m","tthird":"m","gs":"w","pos":"RCB","press":"np","xp":1.0,"xt":0.0008,"byp":0,"phase":"cr","ch":"hl","x":-1.9,"y":10.8,"xe":-4.3,"ye":0.3,"to":"Eneko Undabarrena"},{"n":"Eneko Undabarrena","p":1,"min":44,"dir":"sr","rng":"m","dist":23.0,"out":"s","third":"m","tthird":"m","gs":"w","pos":"LCB","press":"np","xp":0.997,"xt":0.0008,"byp":0,"phase":"cr","ch":"c","x":-4.1,"y":-1.8,"xe":-3.6,"ye":-24.7,"to":"Koke"},{"n":"Koke","p":1,"min":44,"dir":"sl","rng":"s","dist":10.2,"out":"s","third":"m","tthird":"m","flb":1,"ahead":1,"gs":"w","pos":"RB","press":"lp","xp":0.967,"xt":0.0017,"byp":2,"phase":"cr","ch":"wr","x":-4.5,"y":-24.3,"xe":0.6,"ye":-15.5,"to":"Vicente Esquerdo"},{"n":"Vicente Esquerdo","p":1,"min":44,"dir":"b","rng":"s","dist":13.9,"out":"s","third":"m","tthird":"m","one":1,"gs":"w","pos":"CM","press":"mp","xp":0.992,"xt":0.0005,"byp":-2,"phase":"cr","ch":"hr","x":0.6,"y":-15.5,"xe":-11.2,"ye":-22.9,"to":"Koke"},{"n":"Koke","p":1,"min":44,"dir":"sl","rng":"m","dist":25.3,"out":"s","third":"m","tthird":"d","gs":"w","pos":"RB","press":"np","xp":0.997,"xt":0.0001,"byp":0,"phase":"cr","ch":"wr","x":-13.3,"y":-22.3,"xe":-27.2,"ye":-1.2,"to":"Eneko Undabarrena"},{"n":"Eneko Undabarrena","p":1,"min":44,"dir":"b","rng":"m","dist":16.6,"out":"s","third":"d","tthird":"d","gs":"w","pos":"LCB","press":"lp","xp":0.992,"byp":0,"phase":"bu","ch":"c","x":-29.5,"y":4.3,"xe":-44.8,"ye":-2.2,"to":"Andr\u00e9s Prieto"},{"n":"Andr\u00e9s Prieto","p":1,"min":44,"tdir":"f","out":"u","third":"d","flb":1,"slb":1,"one":1,"ahead":1,"gs":"w","pos":"GK","press":"mp","xp":0.697,"xt":0.0005,"byp":6,"phase":"di","ch":"c","x":-44.8,"y":-2.2,"xe":-2.5,"ye":-16.3,"to":"A. Keita"},{"n":"Germ\u00e1n Novoa","p":1,"min":44,"tdir":"f","out":"u","third":"d","ahead":1,"gs":"w","pos":"RCB","press":"mp","xp":0.774,"xt":0.0015,"byp":4,"phase":"ds","ch":"c","x":-33.7,"y":4.4,"xe":-20.0,"ye":3.2,"to":"E. Frimpong"},{"n":"P. Ferrer","p":1,"min":45,"dir":"sr","rng":"s","dist":8.9,"out":"s","third":"d","tthird":"d","one":1,"header":1,"gs":"w","pos":"CF","phase":"ch","ch":"c","x":-32.4,"y":-4.5,"xe":-26.6,"ye":-11.3,"to":"A. Keita"},{"n":"A. Keita","p":1,"min":46,"dir":"b","rng":"s","dist":4.1,"out":"s","third":"d","tthird":"d","one":1,"gs":"w","pos":"LF","press":"hp","xp":0.96,"xt":0.001,"byp":-2,"phase":"tr","ch":"hr","x":-31.3,"y":-13.4,"xe":-35.2,"ye":-14.1,"to":"P. Ferrer"},{"n":"P. Ferrer","p":1,"min":46,"dir":"sl","rng":"m","dist":15.6,"out":"s","third":"d","tthird":"d","one":1,"ahead":1,"gs":"w","pos":"CF","press":"hp","xp":0.898,"xt":0.0021,"byp":2,"phase":"tr","ch":"hr","x":-35.2,"y":-14.1,"xe":-28.1,"ye":-0.3,"to":"Borja V\u00e1zquez"},{"n":"Andoni L\u00f3pez","p":1,"min":46,"tdir":"f","out":"u","third":"d","gs":"w","pos":"LB","press":"mp","xp":0.691,"xt":0.0108,"byp":1,"phase":"tr","ch":"hl","x":-4.0,"y":8.0,"xe":-3.7,"ye":10.5,"to":"E. Frimpong"},{"n":"Vicente Esquerdo","p":1,"min":47,"dir":"sr","rng":"m","dist":29.4,"out":"s","third":"m","tthird":"m","gs":"w","pos":"CM","xp":0.998,"xt":0.0007,"byp":0,"phase":"cr","ch":"c","x":-1.3,"y":4.4,"xe":-4.6,"ye":-24.8,"to":"Koke"},{"n":"Koke","p":1,"min":47,"dir":"f","rng":"s","dist":13.5,"out":"s","third":"m","tthird":"m","flb":1,"ahead":1,"gs":"w","pos":"RB","press":"np","xp":0.974,"xt":0.0015,"byp":3,"phase":"cr","ch":"wr","x":-4.0,"y":-25.1,"xe":9.3,"ye":-23.4,"to":"P. Ferrer"},{"n":"P. Ferrer","p":1,"min":47,"dir":"sl","rng":"s","dist":11.3,"out":"s","third":"m","tthird":"m","gs":"w","pos":"CF","press":"mp","xp":0.909,"xt":0.0059,"byp":0,"phase":"cr","ch":"wr","x":7.4,"y":-21.6,"xe":5.5,"ye":-10.5,"to":"Vicente Esquerdo"},{"n":"Vicente Esquerdo","p":1,"min":47,"dir":"sr","rng":"m","dist":17.9,"out":"s","third":"m","tthird":"m","one":1,"gs":"w","pos":"CM","press":"mp","xp":0.995,"xt":0.0006,"byp":-3,"phase":"cr","ch":"hr","x":5.5,"y":-10.5,"xe":-7.1,"ye":-23.2,"to":"Koke"},{"n":"Koke","p":1,"min":47,"dir":"sl","rng":"m","dist":18.9,"out":"s","third":"m","tthird":"m","one":1,"gs":"w","pos":"RB","press":"np","xp":0.999,"byp":0,"phase":"cr","ch":"wr","x":-7.1,"y":-23.2,"xe":-13.3,"ye":-5.3,"to":"Eneko Undabarrena"},{"n":"Eneko Undabarrena","p":1,"min":47,"dir":"sl","rng":"s","dist":6.7,"out":"s","third":"m","tthird":"m","ahead":1,"gs":"w","pos":"LCB","press":"np","xp":0.994,"xt":0.0007,"byp":0,"phase":"cr","ch":"c","x":-13.3,"y":-3.8,"xe":-8.8,"ye":1.1,"to":"E. Frimpong"},{"n":"E. Frimpong","p":1,"min":47,"dir":"sr","rng":"m","dist":23.2,"out":"s","third":"m","tthird":"m","gs":"w","pos":"LM","press":"np","xp":0.997,"xt":0.0005,"byp":0,"phase":"cr","ch":"c","x":-9.3,"y":1.3,"xe":-14.1,"ye":-21.4,"to":"Koke"},{"n":"Koke","p":1,"min":47,"dir":"f","rng":"s","dist":13.5,"out":"s","third":"m","tthird":"m","flb":1,"one":1,"ahead":1,"gs":"w","pos":"RB","press":"lp","xp":0.991,"xt":0.0008,"byp":3,"phase":"cr","ch":"wr","x":-14.1,"y":-21.4,"xe":-2.4,"ye":-28.0,"to":"P. Ferrer"},{"n":"P. Ferrer","p":1,"min":47,"dir":"sl","rng":"s","dist":10.8,"out":"s","third":"m","tthird":"m","gs":"w","pos":"CF","press":"lp","xp":0.992,"xt":0.0023,"byp":-1,"phase":"cr","ch":"wr","x":2.5,"y":-27.4,"xe":0.3,"ye":-16.8,"to":"E. Frimpong"},{"n":"E. Frimpong","p":1,"min":47,"tdir":"f","out":"u","third":"m","ahead":1,"gs":"w","pos":"LM","press":"np","xp":0.767,"xt":0.0036,"byp":1,"phase":"cr","ch":"hr","x":1.6,"y":-15.8,"xe":6.4,"ye":29.1,"to":"Andoni L\u00f3pez"},{"n":"Andr\u00e9s Prieto","p":1,"min":49,"tdir":"f","out":"u","third":"d","flb":1,"slb":1,"one":1,"ahead":1,"gs":"w","pos":"GK","xp":0.903,"xt":0.0002,"byp":4,"phase":"di","ch":"c","x":-45.4,"y":-7.0,"xe":8.5,"ye":-12.6,"to":"A. Keita"},{"n":"Borja V\u00e1zquez","p":1,"min":50,"dir":"f","rng":"s","dist":8.8,"out":"s","third":"m","tthird":"a","ahead":1,"gs":"w","pos":"RM","press":"lp","xp":0.654,"xt":0.0147,"byp":3,"phase":"tr","ch":"wl","x":26.7,"y":27.1,"xe":35.3,"ye":25.5,"to":"A. Keita"},{"n":"Andr\u00e9s Prieto","p":2,"min":45,"dir":"sr","rng":"m","dist":16.0,"out":"s","third":"d","tthird":"d","gs":"w","pos":"GK","xp":0.999,"byp":0,"phase":"cr","ch":"c","x":36.7,"y":-6.9,"xe":35.1,"ye":8.9,"to":"Eneko Undabarrena"},{"n":"Eneko Undabarrena","p":2,"min":45,"dir":"sr","rng":"m","dist":24.2,"out":"s","third":"d","tthird":"d","ahead":1,"gs":"w","pos":"LCB","press":"lp","xp":0.998,"xt":0.0001,"byp":2,"phase":"cr","ch":"c","x":32.1,"y":12.1,"xe":21.0,"ye":33.5,"to":"Carlos Calder\u00f3n"},{"n":"Carlos Calder\u00f3n","p":2,"min":45,"dir":"f","rng":"s","dist":8.8,"out":"s","third":"d","tthird":"m","slb":1,"ahead":1,"gs":"w","pos":"RF","press":"mp","xp":0.745,"xt":0.0005,"byp":3,"phase":"cr","ch":"wr","x":20.9,"y":33.4,"xe":14.5,"ye":27.4,"to":"P. Ferrer"},{"n":"P. Ferrer","p":2,"min":45,"dir":"b","rng":"s","dist":6.6,"out":"s","third":"m","tthird":"d","gs":"w","pos":"CF","press":"hp","xp":0.755,"xt":0.0003,"byp":-2,"phase":"bu","ch":"wr","x":20.2,"y":30.2,"xe":25.2,"ye":26.1,"to":"Vicente Esquerdo"},{"n":"Vicente Esquerdo","p":2,"min":45,"dir":"sl","rng":"m","dist":15.4,"out":"s","third":"d","tthird":"d","gs":"w","pos":"CM","press":"mp","xp":0.929,"xt":0.0001,"byp":-1,"phase":"bu","ch":"wr","x":27.1,"y":27.2,"xe":33.4,"ye":13.1,"to":"Eneko Undabarrena"},{"n":"Eneko Undabarrena","p":2,"min":45,"dir":"sl","rng":"m","dist":20.3,"out":"s","third":"d","tthird":"d","gs":"w","pos":"LCB","press":"lp","xp":0.999,"byp":0,"phase":"bu","ch":"hr","x":38.9,"y":7.0,"xe":47.2,"ye":-11.6,"to":"Andr\u00e9s Prieto"},{"n":"Andr\u00e9s Prieto","p":2,"min":45,"dir":"f","rng":"m","dist":19.0,"out":"s","third":"d","tthird":"d","high":1,"one":1,"ahead":1,"gs":"w","pos":"GK","press":"hp","xp":0.693,"xt":0.0004,"byp":1,"phase":"bu","ch":"hl","x":47.2,"y":-11.6,"xe":29.6,"ye":-18.6,"to":"Germ\u00e1n Novoa"},{"n":"Germ\u00e1n Novoa","p":2,"min":45,"dir":"f","rng":"s","dist":9.2,"out":"s","third":"d","tthird":"d","one":1,"ahead":1,"header":1,"gs":"w","pos":"RCB","xp":0.711,"xt":0.0018,"byp":2,"phase":"bu","ch":"hl","x":29.6,"y":-18.6,"xe":20.4,"ye":-18.3,"to":"E. Frimpong"},{"n":"E. Frimpong","p":2,"min":45,"tdir":"sl","out":"u","third":"d","one":1,"ahead":1,"header":1,"diff":1,"gs":"w","pos":"LM","xp":0.545,"xt":0.0035,"byp":4,"phase":"bu","ch":"hl","x":20.4,"y":-18.3,"xe":7.9,"ye":-12.4,"to":"A. Keita"},{"n":"P. Ferrer","p":2,"min":46,"dir":"b","rng":"s","dist":6.9,"out":"s","third":"d","tthird":"d","one":1,"gs":"w","pos":"CF","press":"hp","xp":0.707,"xt":0.0024,"byp":-2,"phase":"tr","ch":"c","x":18.0,"y":-5.3,"xe":23.2,"ye":-9.8,"to":"A. Keita"},{"n":"A. Keita","p":2,"min":46,"tdir":"sl","out":"u","third":"d","ahead":1,"gs":"w","pos":"LF","press":"mp","xp":0.772,"xt":0.009,"byp":2,"phase":"tr","ch":"hl","x":21.9,"y":-12.9,"xe":15.8,"ye":-18.8,"to":"Borja V\u00e1zquez"},{"n":"Borja V\u00e1zquez","p":2,"min":46,"tdir":"b","out":"u","third":"m","one":1,"dng":1,"header":1,"diff":1,"gs":"w","pos":"RM","xp":0.457,"xt":0.0207,"byp":1,"phase":"ch","ch":"wl","x":-11.1,"y":-29.7,"xe":-12.9,"ye":-18.6,"to":"P. Ferrer"},{"n":"Vicente Esquerdo","p":2,"min":47,"dir":"f","rng":"s","dist":9.6,"out":"s","third":"m","tthird":"m","flb":1,"slb":1,"ahead":1,"diff":1,"gs":"w","pos":"CM","press":"mp","xp":0.642,"xt":0.0048,"byp":5,"phase":"ch","ch":"wl","x":9.8,"y":-26.2,"xe":0.7,"ye":-23.6,"to":"A. Keita"},{"n":"Vicente Esquerdo","p":2,"min":47,"dir":"sr","rng":"m","dist":15.2,"out":"s","third":"m","tthird":"m","high":1,"ahead":1,"gs":"w","pos":"CM","press":"lp","xp":0.891,"xt":0.012,"byp":1,"phase":"qb","ch":"c","x":-7.9,"y":-0.7,"xe":-15.0,"ye":12.8,"to":"Carlos Calder\u00f3n"},{"n":"Carlos Calder\u00f3n","p":2,"min":47,"dir":"b","rng":"s","dist":14.0,"out":"s","third":"m","tthird":"m","gs":"w","pos":"RF","press":"mp","xp":0.987,"xt":0.0011,"byp":-2,"phase":"qb","ch":"hr","x":-15.0,"y":13.4,"xe":-4.4,"ye":22.5,"to":"Koke"},{"n":"Koke","p":2,"min":47,"dir":"f","rng":"s","dist":14.3,"out":"s","third":"m","tthird":"a","flb":1,"one":1,"ahead":1,"gs":"w","pos":"RB","press":"mp","xp":0.666,"xt":0.006,"byp":3,"phase":"qb","ch":"wr","x":-4.4,"y":22.5,"xe":-18.1,"ye":26.8,"to":"Carlos Calder\u00f3n"},{"n":"Eneko Undabarrena","p":2,"min":47,"dir":"sl","rng":"s","dist":6.8,"out":"s","third":"m","tthird":"m","ahead":1,"gs":"w","pos":"LCB","press":"lp","xp":0.916,"xt":0.006,"byp":1,"phase":"fi","ch":"hr","x":-13.4,"y":16.8,"xe":-17.2,"ye":11.1,"to":"E. Frimpong"},{"n":"E. Frimpong","p":2,"min":47,"dir":"sl","rng":"m","dist":19.1,"out":"s","third":"m","tthird":"m","gs":"w","pos":"LM","press":"mp","xp":0.987,"xt":0.0023,"byp":-3,"phase":"fi","ch":"hr","x":-15.2,"y":11.4,"xe":-3.6,"ye":-3.8,"to":"Andoni L\u00f3pez"},{"n":"Andoni L\u00f3pez","p":2,"min":47,"dir":"sl","rng":"m","dist":18.8,"out":"s","third":"m","tthird":"a","ahead":1,"gs":"w","pos":"LB","press":"np","xp":0.995,"xt":0.005,"byp":1,"phase":"fi","ch":"c","x":-13.3,"y":-12.2,"xe":-21.7,"ye":-29.0,"to":"Borja V\u00e1zquez"},{"n":"Borja V\u00e1zquez","p":2,"min":47,"dir":"sr","rng":"m","dist":18.8,"out":"s","third":"a","tthird":"a","gs":"w","pos":"RM","press":"lp","xp":0.992,"xt":0.0068,"byp":0,"phase":"fi","ch":"wl","x":-25.3,"y":-27.4,"xe":-19.7,"ye":-9.5,"to":"Vicente Esquerdo"},{"n":"Vicente Esquerdo","p":2,"min":47,"dir":"f","rng":"s","dist":9.8,"out":"s","third":"a","tthird":"a","flb":1,"slb":1,"ahead":1,"gs":"w","pos":"CM","press":"lp","xp":0.901,"xt":0.0123,"byp":4,"phase":"fi","ch":"hl","x":-20.9,"y":-12.7,"xe":-28.6,"ye":-18.8,"to":"Andoni L\u00f3pez"},{"n":"Andoni L\u00f3pez","p":2,"min":47,"dir":"b","rng":"s","dist":8.4,"out":"s","third":"a","tthird":"a","one":1,"gs":"w","pos":"LB","press":"hp","xp":0.948,"xt":0.0046,"byp":-4,"phase":"fi","ch":"hl","x":-28.6,"y":-18.8,"xe":-20.7,"ye":-16.1,"to":"Vicente Esquerdo"},{"n":"Vicente Esquerdo","p":2,"min":47,"dir":"sl","rng":"s","dist":14.0,"out":"s","third":"a","tthird":"a","gs":"w","pos":"CM","press":"lp","xp":0.988,"xt":0.0051,"byp":1,"phase":"fi","ch":"hl","x":-20.0,"y":-19.4,"xe":-24.2,"ye":-32.7,"to":"Borja V\u00e1zquez"},{"n":"Borja V\u00e1zquez","p":2,"min":47,"tdir":"sl","out":"u","third":"a","ahead":1,"diff":1,"gs":"w","pos":"RM","press":"lp","xp":0.543,"xt":0.0167,"byp":3,"phase":"fi","ch":"wl","x":-24.1,"y":-32.9,"xe":-31.2,"ye":-9.8,"to":"A. Keita"},{"n":"A. Keita","p":2,"min":47,"tdir":"f","out":"u","third":"a","dng":1,"diff":1,"gs":"w","pos":"LF","press":"hp","xp":0.35,"xt":0.1211,"byp":-4,"phase":"fi","ch":"hl","x":-42.9,"y":-12.8,"xe":-36.2,"ye":-5.9,"to":"E. Frimpong"},{"n":"Eneko Undabarrena","p":2,"min":49,"dir":"f","rng":"m","dist":29.7,"out":"s","third":"d","tthird":"m","flb":1,"slb":1,"high":1,"one":1,"ahead":1,"diff":1,"gs":"w","pos":"LCB","press":"mp","xp":0.549,"xt":0.0073,"byp":7,"phase":"cr","ch":"hl","x":19.6,"y":-19.0,"xe":-10.0,"ye":-16.3,"to":"A. Keita"},{"n":"A. Keita","p":2,"min":49,"dir":"f","rng":"s","dist":12.8,"out":"s","third":"m","tthird":"a","one":1,"dng":1,"ahead":1,"diff":1,"gs":"w","pos":"LF","press":"mp","xp":0.39,"xt":0.0633,"byp":3,"phase":"cr","ch":"hl","x":-10.0,"y":-16.3,"xe":-22.3,"ye":-20.1,"to":"P. Ferrer"},{"n":"P. Ferrer","p":2,"min":50,"dir":"f","rng":"s","dist":8.8,"out":"s","third":"a","tthird":"a","dng":1,"diff":1,"gs":"w","pos":"CF","press":"hp","xp":0.627,"xt":0.035,"byp":4,"phase":"fi","ch":"hl","x":-34.9,"y":-18.7,"xe":-42.7,"ye":-22.8,"to":"A. Keita"},{"n":"A. Keita","p":2,"min":50,"tdir":"f","out":"o","third":"a","dng":1,"diff":1,"gs":"w","pos":"LF","press":"hp","xp":0.228,"xt":0.0721,"byp":-3,"phase":"fi","ch":"wl","x":-48.9,"y":-23.0,"xe":-43.8,"ye":-11.8,"to":"P. Ferrer"},{"n":"Vicente Esquerdo","p":2,"min":50,"dir":"b","rng":"m","dist":17.8,"out":"s","third":"m","tthird":"d","gs":"w","pos":"CM","xp":0.998,"xt":0.0003,"byp":-2,"phase":"cr","ch":"hl","x":9.2,"y":-17.8,"xe":24.9,"ye":-9.2,"to":"Eneko Undabarrena"},{"n":"Eneko Undabarrena","p":2,"min":50,"dir":"sr","rng":"l","dist":36.3,"out":"s","third":"d","tthird":"m","ahead":1,"gs":"w","pos":"LCB","press":"np","xp":0.991,"xt":0.0004,"byp":2,"phase":"bu","ch":"hl","x":25.1,"y":-7.1,"xe":8.9,"ye":25.4,"to":"Koke"},{"n":"Koke","p":2,"min":51,"tdir":"f","out":"u","third":"m","flb":1,"llb":1,"slb":1,"ahead":1,"diff":1,"gs":"w","pos":"RB","press":"lp","xp":0.389,"xt":0.0136,"byp":7,"phase":"cr","ch":"wr","x":-1.4,"y":26.9,"xe":-20.6,"ye":18.5,"to":"Carlos Calder\u00f3n"},{"n":"E. Frimpong","p":2,"min":51,"dir":"sr","rng":"s","dist":13.8,"out":"s","third":"m","tthird":"m","one":1,"gs":"w","pos":"LM","press":"mp","xp":0.987,"xt":0.0062,"byp":-2,"phase":"qb","ch":"wl","x":-13.4,"y":-20.5,"xe":-4.7,"ye":-9.9,"to":"Vicente Esquerdo"},{"n":"Vicente Esquerdo","p":2,"min":51,"dir":"sl","rng":"s","dist":7.5,"out":"s","third":"m","tthird":"m","ahead":1,"gs":"w","pos":"CM","press":"np","xp":0.948,"xt":0.0078,"byp":0,"phase":"qb","ch":"hl","x":-11.7,"y":-13.4,"xe":-16.4,"ye":-19.3,"to":"A. Keita"},{"n":"A. Keita","p":2,"min":51,"dir":"sl","rng":"s","dist":13.4,"out":"s","third":"m","tthird":"a","gs":"w","pos":"LF","press":"lp","xp":0.986,"xt":0.0087,"byp":2,"phase":"qb","ch":"hl","x":-18.7,"y":-19.2,"xe":-26.4,"ye":-30.1,"to":"Borja V\u00e1zquez"},{"n":"Borja V\u00e1zquez","p":2,"min":51,"dir":"b","rng":"s","dist":13.3,"out":"s","third":"a","tthird":"a","gs":"w","pos":"RM","press":"lp","xp":0.997,"xt":0.0056,"byp":-3,"phase":"qb","ch":"wl","x":-38.4,"y":-31.6,"xe":-25.1,"ye":-31.6,"to":"E. Frimpong"},{"n":"E. Frimpong","p":2,"min":51,"dir":"sr","rng":"m","dist":17.6,"out":"s","third":"a","tthird":"m","gs":"w","pos":"LM","press":"np","xp":0.998,"xt":0.004,"byp":-2,"phase":"fi","ch":"wl","x":-24.6,"y":-31.4,"xe":-13.9,"ye":-17.4,"to":"Germ\u00e1n Novoa"},{"n":"Germ\u00e1n Novoa","p":2,"min":51,"dir":"sr","rng":"m","dist":18.5,"out":"s","third":"m","tthird":"m","gs":"w","pos":"RCB","press":"lp","xp":0.998,"xt":0.0028,"byp":0,"phase":"fi","ch":"hl","x":-13.6,"y":-19.3,"xe":-7.7,"ye":-1.7,"to":"Eneko Undabarrena"},{"n":"Eneko Undabarrena","p":2,"min":51,"dir":"sl","rng":"s","dist":14.9,"out":"s","third":"m","tthird":"m","gs":"w","pos":"LCB","press":"np","xp":0.998,"xt":0.0024,"byp":0,"phase":"fi","ch":"c","x":-8.2,"y":-0.7,"xe":-9.8,"ye":-15.5,"to":"Germ\u00e1n Novoa"},{"n":"Germ\u00e1n Novoa","p":2,"min":51,"dir":"sl","rng":"m","dist":20.2,"out":"s","third":"m","tthird":"a","ahead":1,"gs":"w","pos":"RCB","press":"np","xp":0.995,"xt":0.0028,"byp":4,"phase":"fi","ch":"hl","x":-10.9,"y":-17.2,"xe":-24.5,"ye":-32.2,"to":"Borja V\u00e1zquez"},{"n":"Borja V\u00e1zquez","p":2,"min":51,"dir":"sr","rng":"s","dist":13.6,"out":"s","third":"a","tthird":"a","ahead":1,"gs":"w","pos":"RM","press":"np","xp":0.726,"xt":0.0176,"byp":1,"phase":"fi","ch":"wl","x":-26.1,"y":-31.8,"xe":-32.6,"ye":-19.9,"to":"Andoni L\u00f3pez"},{"n":"Andoni L\u00f3pez","p":2,"min":51,"dir":"sl","rng":"s","dist":12.6,"out":"s","third":"a","tthird":"a","one":1,"gs":"w","pos":"LB","press":"hp","xp":0.822,"xt":0.0097,"byp":2,"phase":"fi","ch":"hl","x":-32.6,"y":-19.9,"xe":-38.7,"ye":-30.9,"to":"Borja V\u00e1zquez"},{"n":"Borja V\u00e1zquez","p":2,"min":51,"dir":"b","rng":"m","dist":19.4,"out":"s","third":"a","tthird":"a","gs":"w","pos":"RM","press":"mp","xp":0.945,"xt":0.004,"byp":-6,"phase":"fi","ch":"wl","x":-39.4,"y":-29.5,"xe":-21.5,"ye":-22.1,"to":"Germ\u00e1n Novoa"},{"n":"Andoni L\u00f3pez","p":2,"min":51,"dir":"f","rng":"s","dist":5.8,"out":"s","third":"a","tthird":"a","one":1,"ahead":1,"gs":"w","pos":"LB","press":"lp","xp":0.951,"xt":0.0032,"byp":3,"phase":"fi","ch":"wl","x":-28.2,"y":-29.0,"xe":-33.6,"ye":-31.4,"to":"Borja V\u00e1zquez"},{"n":"Koke","p":2,"min":52,"dir":"b","rng":"l","dist":33.7,"out":"s","third":"m","tthird":"d","gs":"w","pos":"RB","xp":0.997,"byp":0,"phase":"cr","ch":"c","x":-1.0,"y":0.9,"xe":32.6,"ye":-2.4,"to":"Andr\u00e9s Prieto"},{"n":"Germ\u00e1n Novoa","p":2,"min":52,"dir":"sr","rng":"m","dist":19.7,"out":"s","third":"m","tthird":"d","gs":"w","pos":"RCB","press":"np","xp":1.0,"xt":0.0003,"byp":0,"phase":"cr","ch":"wl","x":13.5,"y":-20.9,"xe":18.0,"ye":-1.8,"to":"Eneko Undabarrena"},{"n":"Eneko Undabarrena","p":2,"min":52,"dir":"f","rng":"l","dist":45.5,"out":"s","third":"d","tthird":"a","slb":1,"high":1,"ahead":1,"diff":1,"gs":"w","pos":"LCB","press":"np","xp":0.471,"xt":0.0162,"byp":8,"phase":"di","ch":"c","x":15.3,"y":6.0,"xe":-27.6,"ye":21.2,"to":"A. Keita"},{"n":"Andoni L\u00f3pez","p":2,"min":53,"dir":"sr","rng":"m","dist":20.3,"out":"s","third":"m","tthird":"a","slb":1,"dng":1,"ahead":1,"gs":"w","pos":"LB","press":"np","xp":0.974,"xt":0.0289,"byp":3,"phase":"tr","ch":"hl","x":-12.1,"y":-16.9,"xe":-22.1,"ye":0.8,"to":"E. Frimpong"},{"n":"E. Frimpong","p":2,"min":53,"dir":"b","rng":"s","dist":4.9,"out":"s","third":"a","tthird":"a","gs":"w","pos":"LM","press":"hp","xp":0.986,"xt":0.0149,"byp":0,"phase":"tr","ch":"c","x":-22.9,"y":-0.9,"xe":-18.5,"ye":-3.1,"to":"Vicente Esquerdo"},{"n":"Vicente Esquerdo","p":2,"min":53,"tdir":"sr","out":"u","third":"a","one":1,"gs":"w","pos":"CM","press":"mp","xp":0.826,"xt":0.0138,"byp":0,"phase":"tr","ch":"c","x":-18.5,"y":-3.1,"xe":-17.4,"ye":16.3,"to":"Koke"},{"n":"Koke","p":2,"min":53,"dir":"b","rng":"m","dist":23.7,"out":"s","third":"m","tthird":"m","gs":"w","pos":"RB","press":"np","xp":0.997,"xt":0.0006,"byp":-1,"phase":"fi","ch":"wr","x":-8.3,"y":22.1,"xe":9.3,"ye":6.3,"to":"Eneko Undabarrena"},{"n":"Eneko Undabarrena","p":2,"min":53,"dir":"sl","rng":"m","dist":24.7,"out":"s","third":"m","tthird":"m","one":1,"ahead":1,"gs":"w","pos":"LCB","press":"lp","xp":0.997,"xt":0.0006,"byp":1,"phase":"cr","ch":"c","x":9.3,"y":6.3,"xe":7.0,"ye":-18.3,"to":"Germ\u00e1n Novoa"},{"n":"Vicente Esquerdo","p":2,"min":54,"dir":"sr","rng":"m","dist":26.2,"out":"s","third":"m","tthird":"m","ahead":1,"gs":"w","pos":"CM","xp":0.994,"xt":0.0018,"byp":-1,"phase":"cr","ch":"c","x":-5.2,"y":4.2,"xe":-7.8,"ye":30.3,"to":"Carlos Calder\u00f3n"},{"n":"Carlos Calder\u00f3n","p":2,"min":54,"dir":"b","rng":"s","dist":12.0,"out":"s","third":"m","tthird":"m","gs":"w","pos":"RF","press":"mp","xp":0.995,"xt":0.0005,"byp":-3,"phase":"cr","ch":"wr","x":-8.3,"y":31.9,"xe":2.8,"ye":27.5,"to":"Koke"},{"n":"Koke","p":2,"min":54,"dir":"sl","rng":"m","dist":28.2,"out":"s","third":"m","tthird":"d","gs":"w","pos":"RB","press":"lp","xp":0.997,"xt":0.0003,"byp":0,"phase":"cr","ch":"wr","x":3.9,"y":27.1,"xe":19.1,"ye":3.4,"to":"Eneko Undabarrena"},{"n":"Eneko Undabarrena","p":2,"min":54,"dir":"sr","rng":"m","dist":21.3,"out":"s","third":"d","tthird":"d","gs":"w","pos":"LCB","press":"np","xp":0.998,"xt":0.0001,"byp":0,"phase":"bu","ch":"c","x":29.2,"y":-11.2,"xe":35.9,"ye":9.0,"to":"Andr\u00e9s Prieto"},{"n":"Andr\u00e9s Prieto","p":2,"min":54,"dir":"f","rng":"l","dist":32.2,"out":"s","third":"d","tthird":"m","flb":1,"slb":1,"high":1,"ahead":1,"diff":1,"gs":"w","pos":"GK","press":"np","xp":0.639,"xt":0.0038,"byp":6,"phase":"bu","ch":"c","x":29.7,"y":11.2,"xe":0.1,"ye":-1.3,"to":"A. Keita"},{"n":"A. Keita","p":2,"min":54,"tdir":"f","out":"u","third":"m","llb":1,"dng":1,"ahead":1,"gs":"w","pos":"LF","press":"hp","xp":0.727,"xt":0.0283,"byp":6,"phase":"fi","ch":"c","x":-25.5,"y":22.4,"xe":-35.1,"ye":25.4,"to":"Carlos Calder\u00f3n"},{"n":"Eneko Undabarrena","p":2,"min":55,"dir":"sl","rng":"s","dist":11.2,"out":"s","third":"m","tthird":"d","gs":"w","pos":"LCB","press":"mp","xp":0.999,"xt":0.0002,"byp":0,"phase":"cr","ch":"c","x":15.2,"y":7.5,"xe":19.7,"ye":-2.7,"to":"Germ\u00e1n Novoa"},{"n":"Germ\u00e1n Novoa","p":2,"min":55,"dir":"sl","rng":"m","dist":25.3,"out":"s","third":"d","tthird":"m","ahead":1,"gs":"w","pos":"RCB","press":"np","xp":0.997,"xt":0.0005,"byp":2,"phase":"cr","ch":"c","x":18.9,"y":-3.9,"xe":5.0,"ye":-25.0,"to":"Andoni L\u00f3pez"},{"n":"E. Frimpong","p":2,"min":55,"dir":"sr","rng":"s","dist":9.6,"out":"s","third":"m","tthird":"m","gs":"w","pos":"LM","xp":0.979,"xt":0.0051,"byp":1,"phase":"cr","ch":"hl","x":-3.7,"y":-14.5,"xe":-6.7,"ye":-5.4,"to":"Vicente Esquerdo"},{"n":"Vicente Esquerdo","p":2,"min":55,"dir":"sl","rng":"s","dist":7.3,"out":"s","third":"m","tthird":"m","one":1,"gs":"w","pos":"CM","press":"mp","xp":0.963,"xt":0.0031,"byp":-2,"phase":"cr","ch":"c","x":-6.7,"y":-5.4,"xe":-2.7,"ye":-11.4,"to":"E. Frimpong"},{"n":"E. Frimpong","p":2,"min":55,"dir":"sr","rng":"m","dist":21.7,"out":"s","third":"m","tthird":"m","one":1,"gs":"w","pos":"LM","press":"mp","xp":0.997,"xt":0.0008,"byp":0,"phase":"cr","ch":"hl","x":-2.7,"y":-11.4,"xe":10.9,"ye":5.5,"to":"Eneko Undabarrena"},{"n":"Eneko Undabarrena","p":2,"min":55,"dir":"sr","rng":"m","dist":26.8,"out":"s","third":"m","tthird":"m","ahead":1,"gs":"w","pos":"LCB","press":"np","xp":0.991,"xt":0.0013,"byp":2,"phase":"cr","ch":"c","x":10.0,"y":8.3,"xe":-4.9,"ye":30.6,"to":"Koke"},{"n":"Koke","p":2,"min":55,"dir":"sl","rng":"s","dist":7.0,"out":"s","third":"m","tthird":"m","gs":"w","pos":"RB","press":"lp","xp":0.989,"xt":0.0019,"byp":0,"phase":"cr","ch":"wr","x":-5.8,"y":29.2,"xe":-5.0,"ye":22.2,"to":"Vicente Esquerdo"},{"n":"Vicente Esquerdo","p":2,"min":55,"dir":"f","rng":"m","dist":16.3,"out":"s","third":"m","tthird":"a","flb":1,"slb":1,"ahead":1,"gs":"w","pos":"CM","press":"mp","xp":0.79,"xt":0.0085,"byp":5,"phase":"cr","ch":"wr","x":-5.0,"y":24.4,"xe":-21.2,"ye":22.7,"to":"Carlos Calder\u00f3n"},{"n":"Carlos Calder\u00f3n","p":2,"min":55,"dir":"b","rng":"s","dist":6.2,"out":"s","third":"a","tthird":"m","one":1,"gs":"w","pos":"RF","press":"mp","xp":0.928,"xt":0.0134,"byp":-3,"phase":"cr","ch":"wr","x":-21.2,"y":22.7,"xe":-15.5,"ye":20.2,"to":"Koke"},{"n":"Koke","p":2,"min":55,"tdir":"f","out":"o","third":"m","llb":1,"dng":1,"ahead":1,"diff":1,"gs":"w","pos":"RB","press":"mp","xp":0.458,"xt":0.0509,"byp":6,"phase":"cr","ch":"wr","x":-15.8,"y":19.9,"xe":-24.0,"ye":3.1,"to":"P. Ferrer"},{"n":"Andr\u00e9s Prieto","p":2,"min":56,"tdir":"sl","out":"u","third":"d","slb":1,"ahead":1,"gs":"w","pos":"GK","xp":0.699,"xt":0.0015,"byp":6,"phase":"di","ch":"c","x":39.3,"y":-3.4,"xe":2.3,"ye":-13.6,"to":"Borja V\u00e1zquez"},{"n":"Andoni L\u00f3pez","p":2,"min":57,"dir":"f","rng":"m","dist":17.0,"out":"s","third":"m","tthird":"m","ahead":1,"gs":"w","pos":"LB","press":"hp","xp":0.792,"xt":0.0107,"byp":3,"phase":"cr","ch":"wl","x":4.4,"y":-23.8,"xe":-10.8,"ye":-16.1,"to":"A. Keita"},{"n":"A. Keita","p":2,"min":57,"tdir":"sl","out":"u","third":"m","one":1,"dng":1,"gs":"w","pos":"LF","press":"hp","xp":0.848,"xt":0.0283,"byp":-2,"phase":"cr","ch":"hl","x":-10.8,"y":-16.1,"xe":-1.3,"ye":-15.9,"to":"E. Frimpong"},{"n":"Vicente Esquerdo","p":2,"min":57,"dir":"f","rng":"s","dist":14.5,"out":"s","third":"m","tthird":"m","slb":1,"high":1,"ahead":1,"gs":"w","pos":"CM","press":"mp","xp":0.871,"xt":0.0066,"byp":3,"phase":"cr","ch":"wr","x":2.3,"y":17.4,"xe":-10.2,"ye":10.2,"to":"A. Keita"},{"n":"Koke","p":2,"min":57,"dir":"f","rng":"l","dist":50.5,"out":"s","third":"d","tthird":"m","slb":1,"high":1,"ahead":1,"diff":1,"gs":"w","pos":"RB","xp":0.485,"xt":0.0009,"byp":7,"phase":"tr","ch":"hr","x":36.3,"y":28.6,"xe":-14.0,"ye":32.3,"to":"Carlos Calder\u00f3n"},{"n":"Carlos Calder\u00f3n","p":2,"min":57,"dir":"b","rng":"s","dist":13.7,"out":"s","third":"m","tthird":"m","gs":"w","pos":"RF","xp":0.972,"xt":0.0051,"byp":-2,"phase":"tr","ch":"wr","x":-23.9,"y":31.0,"xe":-14.1,"ye":21.4,"to":"P. Ferrer"},{"n":"P. Ferrer","p":2,"min":57,"dir":"b","rng":"s","dist":12.5,"out":"s","third":"m","tthird":"m","gs":"w","pos":"CF","press":"mp","xp":0.981,"xt":0.0012,"byp":-2,"phase":"cr","ch":"wr","x":-8.1,"y":20.9,"xe":4.0,"ye":17.7,"to":"Vicente Esquerdo"},{"n":"Vicente Esquerdo","p":2,"min":58,"dir":"sl","rng":"m","dist":28.5,"out":"s","third":"m","tthird":"m","flb":1,"ahead":1,"gs":"w","pos":"CM","press":"np","xp":0.982,"xt":0.0044,"byp":2,"phase":"cr","ch":"hr","x":2.3,"y":15.1,"xe":-9.7,"ye":-10.8,"to":"Borja V\u00e1zquez"},{"n":"Borja V\u00e1zquez","p":2,"min":58,"dir":"sl","rng":"m","dist":19.5,"out":"s","third":"m","tthird":"m","ahead":1,"gs":"w","pos":"RM","press":"lp","xp":0.993,"xt":0.0046,"byp":0,"phase":"cr","ch":"hl","x":-10.7,"y":-14.0,"xe":-16.3,"ye":-32.6,"to":"Andoni L\u00f3pez"},{"n":"Andoni L\u00f3pez","p":2,"min":58,"dir":"sr","rng":"m","dist":18.2,"out":"s","third":"m","tthird":"a","slb":1,"ahead":1,"gs":"w","pos":"LB","press":"np","xp":0.791,"xt":0.0089,"byp":3,"phase":"fi","ch":"wl","x":-16.3,"y":-30.1,"xe":-25.0,"ye":-14.1,"to":"A. Keita"},{"n":"A. Keita","p":2,"min":58,"dir":"sr","rng":"s","dist":14.6,"out":"s","third":"a","tthird":"m","gs":"w","pos":"LF","press":"mp","xp":0.994,"xt":0.0077,"byp":-2,"phase":"fi","ch":"hl","x":-22.4,"y":-12.5,"xe":-15.3,"ye":0.3,"to":"Vicente Esquerdo"},{"n":"Vicente Esquerdo","p":2,"min":58,"dir":"f","rng":"m","dist":16.9,"out":"s","third":"m","tthird":"a","slb":1,"dng":1,"ahead":1,"gs":"w","pos":"CM","press":"np","xp":0.676,"xt":0.0256,"byp":6,"phase":"fi","ch":"c","x":-15.8,"y":-0.5,"xe":-32.8,"ye":-0.1,"to":"P. Ferrer"},{"n":"Germ\u00e1n Novoa","p":2,"min":59,"dir":"f","rng":"s","dist":9.1,"out":"s","third":"m","tthird":"m","one":1,"ahead":1,"gs":"w","pos":"RCB","press":"mp","xp":0.95,"xt":0.0034,"byp":4,"phase":"tr","ch":"wl","x":14.0,"y":-20.9,"xe":5.4,"ye":-18.0,"to":"Borja V\u00e1zquez"},{"n":"Borja V\u00e1zquez","p":2,"min":59,"dir":"sl","rng":"s","dist":14.2,"out":"s","third":"m","tthird":"a","shot":1,"gs":"w","pos":"RM","press":"lp","xp":0.993,"xt":0.008,"byp":0,"phase":"tr","ch":"hl","x":-17.3,"y":-16.9,"xe":-21.1,"ye":-30.6,"to":"Andoni L\u00f3pez"},{"n":"Andoni L\u00f3pez","p":2,"min":59,"tdir":"f","out":"u","third":"a","dng":1,"shot":1,"ahead":1,"diff":1,"gs":"w","pos":"LB","press":"lp","xp":0.376,"xt":0.0603,"byp":5,"phase":"tr","ch":"wl","x":-24.2,"y":-30.9,"xe":-37.3,"ye":-1.0,"to":"P. Ferrer"},{"n":"Vicente Esquerdo","p":2,"min":60,"dir":"sl","rng":"m","dist":16.3,"out":"s","third":"d","tthird":"m","high":1,"gs":"w","pos":"CM","press":"mp","xp":0.913,"xt":0.0011,"byp":-2,"phase":"cr","ch":"c","x":18.7,"y":-12.3,"xe":15.7,"ye":-28.3,"to":"Borja V\u00e1zquez"},{"n":"Germ\u00e1n Novoa","p":2,"min":60,"dir":"sr","rng":"m","dist":18.0,"out":"s","third":"m","tthird":"d","gs":"w","pos":"RCB","xp":0.999,"xt":0.0005,"byp":0,"phase":"cr","ch":"hl","x":15.7,"y":-16.6,"xe":18.7,"ye":1.1,"to":"Eneko Undabarrena"},{"n":"Eneko Undabarrena","p":2,"min":60,"dir":"sr","rng":"m","dist":21.4,"out":"s","third":"d","tthird":"m","ahead":1,"gs":"w","pos":"LCB","press":"np","xp":0.997,"xt":0.0003,"byp":1,"phase":"cr","ch":"c","x":18.1,"y":5.4,"xe":11.0,"ye":25.6,"to":"Koke"},{"n":"Koke","p":2,"min":60,"tdir":"sl","out":"o","third":"m","llb":1,"slb":1,"ahead":1,"diff":1,"gs":"w","pos":"RB","press":"lp","xp":0.393,"xt":0.0122,"byp":4,"phase":"di","ch":"wr","x":10.9,"y":24.7,"xe":-6.6,"ye":18.9,"to":"P. Ferrer"},{"n":"Germ\u00e1n Novoa","p":2,"min":68,"dir":"sr","rng":"m","dist":15.4,"out":"s","third":"d","tthird":"d","one":1,"header":1,"gs":"w","pos":"RCB","phase":"ch","ch":"c","x":45.7,"y":2.5,"xe":37.8,"ye":15.7,"to":"Eneko Undabarrena"},{"n":"Andr\u00e9s Prieto","p":2,"min":68,"dir":"f","rng":"l","dist":57.6,"out":"s","third":"d","tthird":"a","flb":1,"slb":1,"high":1,"ahead":1,"gs":"w","pos":"GK","xp":0.685,"xt":0.0022,"byp":7,"phase":"di","ch":"c","x":36.6,"y":-5.7,"xe":-20.9,"ye":-7.6,"to":"A. Keita"},{"n":"A. Keita","p":2,"min":68,"tdir":"f","out":"u","third":"a","one":1,"dng":1,"header":1,"diff":1,"gs":"w","pos":"LF","xp":0.33,"xt":0.0762,"byp":0,"phase":"di","ch":"c","x":-20.9,"y":-7.6,"xe":-14.5,"ye":-7.5,"to":"Xemi Fern\u00e1ndez"},{"n":"Koke","p":2,"min":73,"dir":"sl","rng":"s","dist":12.1,"out":"s","third":"d","tthird":"m","ahead":1,"gs":"w","pos":"RB","press":"np","xp":0.924,"xt":0.0008,"byp":4,"phase":"ch","ch":"wr","x":22.2,"y":24.6,"xe":14.1,"ye":15.7,"to":"Fede San Emeterio"},{"n":"Xemi Fern\u00e1ndez","p":2,"min":76,"dir":"sl","rng":"s","dist":11.6,"out":"s","third":"m","tthird":"a","one":1,"dng":1,"header":1,"diff":1,"gs":"w","pos":"LM","xp":0.537,"xt":0.0363,"byp":0,"phase":"cr","ch":"hl","x":-16.5,"y":-14.7,"xe":-23.5,"ye":-24.0,"to":"Jos\u00e9 Luis Cort\u00e9s"},{"n":"Jos\u00e9 Luis Cort\u00e9s","p":2,"min":76,"tdir":"f","out":"u","third":"a","diff":1,"gs":"w","pos":"LF","press":"vhp","xp":0.55,"xt":0.0099,"byp":-4,"phase":"fi","ch":"wl","x":-45.4,"y":-34.4,"xe":-38.2,"ye":-30.3,"to":"Xemi Fern\u00e1ndez"},{"n":"Andoni L\u00f3pez","p":2,"min":76,"dir":"f","rng":"s","dist":11.6,"out":"s","third":"m","tthird":"a","one":1,"header":1,"gs":"w","pos":"LB","phase":"fi","ch":"wl","x":-10.1,"y":-22.4,"xe":-21.5,"ye":-24.8,"to":"Borja V\u00e1zquez"},{"n":"Borja V\u00e1zquez","p":2,"min":76,"dir":"sr","rng":"m","dist":15.7,"out":"s","third":"a","tthird":"m","one":1,"gs":"w","pos":"RM","press":"mp","xp":0.975,"xt":0.0098,"byp":-2,"phase":"fi","ch":"wl","x":-21.5,"y":-24.8,"xe":-16.3,"ye":-10.0,"to":"Fede San Emeterio"},{"n":"Fede San Emeterio","p":2,"min":76,"dir":"sl","rng":"s","dist":6.7,"out":"s","third":"m","tthird":"a","one":1,"ahead":1,"gs":"w","pos":"CF","press":"mp","xp":0.94,"xt":0.0102,"byp":2,"phase":"fi","ch":"hl","x":-16.3,"y":-10.0,"xe":-20.5,"ye":-15.1,"to":"Eneko Undabarrena"},{"n":"Eneko Undabarrena","p":2,"min":76,"dir":"b","rng":"m","dist":15.3,"out":"s","third":"a","tthird":"m","gs":"w","pos":"LCB","press":"mp","xp":0.982,"xt":0.0015,"byp":-2,"phase":"fi","ch":"hl","x":-16.0,"y":-14.3,"xe":-1.7,"ye":-19.5,"to":"Germ\u00e1n Novoa"},{"n":"Germ\u00e1n Novoa","p":2,"min":76,"dir":"f","rng":"s","dist":11.0,"out":"s","third":"m","tthird":"m","flb":1,"ahead":1,"gs":"w","pos":"RCB","press":"np","xp":0.981,"xt":0.0079,"byp":1,"phase":"cr","ch":"hl","x":-2.2,"y":-19.2,"xe":-10.2,"ye":-11.7,"to":"Eneko Undabarrena"},{"n":"Eneko Undabarrena","p":2,"min":76,"dir":"b","rng":"s","dist":6.0,"out":"s","third":"m","tthird":"m","one":1,"gs":"w","pos":"LCB","press":"lp","xp":0.99,"xt":0.0024,"byp":0,"phase":"cr","ch":"hl","x":-10.2,"y":-11.7,"xe":-4.4,"ye":-13.1,"to":"Fede San Emeterio"},{"n":"Fede San Emeterio","p":2,"min":76,"tdir":"sl","out":"u","third":"m","ahead":1,"gs":"w","pos":"CF","press":"lp","xp":0.939,"xt":0.0035,"byp":4,"phase":"cr","ch":"hl","x":-4.2,"y":-13.8,"xe":-13.7,"ye":-22.9,"to":"Xemi Fern\u00e1ndez"},{"n":"Xemi Fern\u00e1ndez","p":2,"min":76,"dir":"b","rng":"s","dist":9.1,"out":"s","third":"m","tthird":"m","one":1,"gs":"w","pos":"LM","press":"mp","xp":0.97,"xt":0.0015,"byp":-2,"phase":"cr","ch":"wl","x":-12.7,"y":-23.3,"xe":-5.2,"ye":-28.4,"to":"Andoni L\u00f3pez"},{"n":"Andoni L\u00f3pez","p":2,"min":76,"dir":"f","rng":"s","dist":14.3,"out":"s","third":"m","tthird":"a","slb":1,"ahead":1,"gs":"w","pos":"LB","press":"np","xp":0.967,"xt":0.0049,"byp":4,"phase":"fi","ch":"wl","x":-7.7,"y":-30.7,"xe":-20.7,"ye":-24.7,"to":"Jos\u00e9 Luis Cort\u00e9s"},{"n":"Jos\u00e9 Luis Cort\u00e9s","p":2,"min":76,"dir":"f","rng":"s","dist":9.5,"out":"s","third":"a","tthird":"a","llb":1,"dng":1,"ahead":1,"diff":1,"gs":"w","pos":"LF","press":"mp","xp":0.624,"xt":0.032,"byp":3,"phase":"fi","ch":"wl","x":-23.2,"y":-31.6,"xe":-31.0,"ye":-26.2,"to":"Borja V\u00e1zquez"},{"n":"David And\u00fajar","p":2,"min":77,"dir":"sl","rng":"s","dist":7.6,"out":"s","third":"d","tthird":"d","one":1,"header":1,"gs":"w","pos":"CM","phase":"bu","ch":"c","x":22.7,"y":-2.6,"xe":22.6,"ye":-10.2,"to":"Germ\u00e1n Novoa"},{"n":"Germ\u00e1n Novoa","p":2,"min":77,"dir":"f","rng":"m","dist":19.6,"out":"s","third":"d","tthird":"m","flb":1,"high":1,"ahead":1,"diff":1,"gs":"w","pos":"RCB","press":"lp","xp":0.529,"xt":0.002,"byp":2,"phase":"bu","ch":"hl","x":32.6,"y":-19.3,"xe":13.2,"ye":-21.1,"to":"Eneko Undabarrena"},{"n":"Eneko Undabarrena","p":2,"min":77,"tdir":"b","out":"u","third":"m","one":1,"ahead":1,"header":1,"diff":1,"gs":"w","pos":"LCB","xp":0.509,"xt":0.0047,"byp":6,"phase":"cr","ch":"wl","x":13.2,"y":-21.1,"xe":-2.8,"ye":-29.9,"to":"Jos\u00e9 Luis Cort\u00e9s"},{"n":"Jos\u00e9 Luis Cort\u00e9s","p":2,"min":78,"dir":"sl","rng":"s","dist":9.5,"out":"s","third":"m","tthird":"m","one":1,"gs":"w","pos":"LF","press":"hp","xp":0.833,"xt":0.0028,"byp":-4,"phase":"cr","ch":"c","x":-1.1,"y":-7.1,"xe":5.3,"ye":-14.1,"to":"Eneko Undabarrena"},{"n":"Eneko Undabarrena","p":2,"min":78,"dir":"b","rng":"m","dist":17.4,"out":"s","third":"m","tthird":"d","one":1,"gs":"w","pos":"LCB","press":"mp","xp":0.99,"xt":0.0004,"byp":-3,"phase":"cr","ch":"hl","x":5.3,"y":-14.1,"xe":21.0,"ye":-21.6,"to":"Andoni L\u00f3pez"},{"n":"Andoni L\u00f3pez","p":2,"min":78,"tdir":"sl","out":"u","third":"d","flb":1,"llb":1,"slb":1,"ahead":1,"diff":1,"gs":"w","pos":"LB","press":"lp","xp":0.473,"xt":0.0111,"byp":7,"phase":"di","ch":"wl","x":20.4,"y":-23.3,"xe":-9.4,"ye":-11.2,"to":"Jos\u00e9 Luis Cort\u00e9s"},{"n":"Carlos Calder\u00f3n","p":2,"min":79,"dir":"sl","rng":"s","dist":6.9,"out":"s","third":"d","tthird":"d","gs":"w","pos":"RF","press":"hp","xp":0.93,"xt":0.0002,"byp":0,"phase":"ch","ch":"hr","x":45.6,"y":18.0,"xe":46.9,"ye":11.2,"to":"Koke"},{"n":"Koke","p":2,"min":79,"tdir":"sr","out":"u","third":"d","one":1,"ahead":1,"diff":1,"gs":"w","pos":"RB","press":"mp","xp":0.414,"xt":0.003,"byp":10,"phase":"di","ch":"hr","x":46.9,"y":11.2,"xe":3.5,"ye":7.5,"to":"Jos\u00e9 Luis Cort\u00e9s"},{"n":"Fede San Emeterio","p":2,"min":80,"tdir":"b","out":"u","third":"m","one":1,"header":1,"gs":"w","pos":"CF","xp":0.867,"xt":0.0005,"byp":-2,"phase":"cr","ch":"wr","x":9.8,"y":21.9,"xe":18.3,"ye":23.4,"to":"David And\u00fajar"},{"n":"Koke","p":2,"min":80,"dir":"f","rng":"m","dist":21.3,"out":"s","third":"d","tthird":"m","high":1,"ahead":1,"diff":1,"gs":"w","pos":"RB","press":"lp","xp":0.546,"xt":0.0017,"byp":5,"phase":"cr","ch":"wr","x":21.6,"y":31.4,"xe":2.0,"ye":22.9,"to":"Xemi Fern\u00e1ndez"},{"n":"Xemi Fern\u00e1ndez","p":2,"min":80,"dir":"sr","rng":"s","dist":7.3,"out":"s","third":"m","tthird":"m","gs":"w","pos":"LM","press":"hp","xp":0.843,"xt":0.0015,"byp":-2,"phase":"cr","ch":"wr","x":0.2,"y":24.7,"xe":3.8,"ye":31.0,"to":"Carlos Calder\u00f3n"},{"n":"Fede San Emeterio","p":2,"min":80,"dir":"sl","rng":"s","dist":11.9,"out":"s","third":"m","tthird":"m","one":1,"ahead":1,"gs":"w","pos":"CF","press":"mp","xp":0.939,"xt":0.0023,"byp":1,"phase":"cr","ch":"wr","x":10.4,"y":24.2,"xe":5.2,"ye":13.5,"to":"Eneko Undabarrena"},{"n":"Eneko Undabarrena","p":2,"min":80,"dir":"sl","rng":"l","dist":36.2,"out":"s","third":"m","tthird":"m","slb":1,"ahead":1,"gs":"w","pos":"LCB","press":"lp","xp":0.906,"xt":0.0064,"byp":2,"phase":"cr","ch":"hr","x":1.8,"y":11.7,"xe":-13.3,"ye":-21.2,"to":"Borja V\u00e1zquez"},{"n":"Jos\u00e9 Luis Cort\u00e9s","p":2,"min":81,"dir":"sl","rng":"m","dist":15.7,"out":"s","third":"m","tthird":"a","dng":1,"gs":"w","pos":"LF","xp":0.946,"xt":0.0234,"byp":1,"phase":"cr","ch":"c","x":-22.4,"y":-6.5,"xe":-27.9,"ye":-21.1,"to":"Borja V\u00e1zquez"},{"n":"Borja V\u00e1zquez","p":2,"min":81,"dir":"sl","rng":"s","dist":8.6,"out":"s","third":"a","tthird":"a","shot":1,"gs":"w","pos":"RM","press":"lp","xp":0.963,"xt":0.0075,"byp":1,"phase":"fi","ch":"wl","x":-27.8,"y":-22.4,"xe":-30.6,"ye":-30.5,"to":"Jos\u00e9 Luis Cort\u00e9s"},{"n":"Jos\u00e9 Luis Cort\u00e9s","p":2,"min":81,"dir":"sr","rng":"s","dist":11.5,"out":"s","third":"a","tthird":"a","dng":1,"shot":1,"box":1,"gs":"w","pos":"LF","press":"mp","xp":0.793,"xt":0.0228,"byp":0,"phase":"fi","ch":"wl","x":-42.1,"y":-18.9,"xe":-40.0,"ye":-7.6,"to":"Carlos Calder\u00f3n"},{"n":"Fede San Emeterio","p":2,"min":83,"tdir":"sr","out":"u","third":"d","ahead":1,"diff":1,"gs":"w","pos":"CF","press":"mp","xp":0.571,"xt":0.0015,"byp":7,"phase":"di","ch":"hr","x":43.6,"y":17.0,"xe":1.1,"ye":17.8,"to":"Jos\u00e9 Luis Cort\u00e9s"},{"n":"Koke","p":2,"min":83,"dir":"sl","rng":"m","dist":16.4,"out":"s","third":"d","tthird":"m","one":1,"gs":"w","pos":"RB","press":"mp","xp":0.962,"xt":0.0015,"byp":-1,"phase":"cr","ch":"wr","x":20.4,"y":20.6,"xe":14.4,"ye":5.3,"to":"Eneko Undabarrena"},{"n":"Eneko Undabarrena","p":2,"min":83,"tdir":"sl","out":"u","third":"m","one":1,"gs":"w","pos":"LCB","press":"hp","xp":0.865,"xt":0.003,"byp":1,"phase":"cr","ch":"c","x":14.4,"y":5.3,"xe":12.5,"ye":-1.9,"to":"Xemi Fern\u00e1ndez"},{"n":"Xemi Fern\u00e1ndez","p":2,"min":83,"dir":"b","rng":"m","dist":16.4,"out":"s","third":"m","tthird":"d","one":1,"gs":"w","pos":"LM","press":"mp","xp":0.987,"xt":0.0002,"byp":-5,"phase":"cr","ch":"c","x":10.9,"y":-2.0,"xe":25.4,"ye":5.8,"to":"David And\u00fajar"},{"n":"David And\u00fajar","p":2,"min":83,"dir":"sl","rng":"s","dist":11.9,"out":"s","third":"d","tthird":"d","one":1,"gs":"w","pos":"CM","press":"np","xp":0.994,"xt":0.0002,"byp":0,"phase":"cr","ch":"c","x":25.4,"y":5.8,"xe":25.6,"ye":-6.1,"to":"Germ\u00e1n Novoa"},{"n":"Germ\u00e1n Novoa","p":2,"min":83,"dir":"f","rng":"s","dist":9.2,"out":"s","third":"d","tthird":"m","flb":1,"ahead":1,"gs":"w","pos":"RCB","press":"np","xp":0.994,"xt":0.0013,"byp":2,"phase":"cr","ch":"c","x":24.0,"y":-9.5,"xe":15.5,"ye":-5.9,"to":"Eneko Undabarrena"},{"n":"Eneko Undabarrena","p":2,"min":83,"dir":"sr","rng":"m","dist":24.9,"out":"s","third":"m","tthird":"m","gs":"w","pos":"LCB","press":"lp","xp":0.994,"xt":0.0003,"byp":0,"phase":"cr","ch":"c","x":16.2,"y":-0.2,"xe":16.0,"ye":24.7,"to":"Koke"},{"n":"Koke","p":2,"min":83,"dir":"sl","rng":"l","dist":45.3,"out":"s","third":"m","tthird":"d","high":1,"gs":"w","pos":"RB","press":"lp","xp":0.973,"xt":0.0001,"byp":-1,"phase":"cr","ch":"wr","x":17.7,"y":21.5,"xe":34.9,"ye":-20.4,"to":"Germ\u00e1n Novoa"},{"n":"Germ\u00e1n Novoa","p":2,"min":83,"dir":"b","rng":"s","dist":14.3,"out":"s","third":"d","tthird":"d","gs":"w","pos":"RCB","press":"lp","xp":0.997,"byp":0,"phase":"bu","ch":"wl","x":37.9,"y":-22.8,"xe":48.1,"ye":-12.7,"to":"Andr\u00e9s Prieto"},{"n":"Andr\u00e9s Prieto","p":2,"min":83,"dir":"f","rng":"l","dist":43.1,"out":"s","third":"d","tthird":"m","flb":1,"slb":1,"high":1,"one":1,"ahead":1,"gs":"w","pos":"GK","xp":0.651,"xt":0.0014,"byp":6,"phase":"di","ch":"hl","x":48.1,"y":-12.7,"xe":6.8,"ye":-25.0,"to":"Xemi Fern\u00e1ndez"},{"n":"Xemi Fern\u00e1ndez","p":2,"min":83,"dir":"b","rng":"s","dist":4.8,"out":"s","third":"m","tthird":"m","gs":"w","pos":"LM","press":"hp","xp":0.99,"xt":0.0023,"byp":-2,"phase":"cr","ch":"wl","x":9.7,"y":-23.9,"xe":14.1,"ye":-22.1,"to":"Fede San Emeterio"},{"n":"Fede San Emeterio","p":2,"min":83,"dir":"sl","rng":"s","dist":9.4,"out":"s","third":"m","tthird":"m","gs":"w","pos":"CF","press":"lp","xp":0.989,"xt":0.0008,"byp":-1,"phase":"cr","ch":"wl","x":14.8,"y":-22.5,"xe":17.4,"ye":-31.6,"to":"Andoni L\u00f3pez"},{"n":"David And\u00fajar","p":2,"min":84,"dir":"sl","rng":"s","dist":14.6,"out":"s","third":"m","tthird":"m","gs":"w","pos":"CM","press":"hp","xp":0.956,"xt":0.0006,"byp":0,"phase":"cr","ch":"c","x":8.3,"y":-7.9,"xe":14.0,"ye":-21.4,"to":"Andoni L\u00f3pez"},{"n":"Andoni L\u00f3pez","p":2,"min":84,"dir":"f","rng":"l","dist":42.4,"out":"s","third":"m","tthird":"a","high":1,"ahead":1,"diff":1,"gs":"w","pos":"LB","press":"lp","xp":0.588,"xt":0.0028,"byp":8,"phase":"di","ch":"wl","x":14.3,"y":-26.9,"xe":-27.8,"ye":-31.8,"to":"Jos\u00e9 Luis Cort\u00e9s"},{"n":"Borislav Ivanov Stankov","p":2,"min":84,"dir":"sl","rng":"m","dist":16.4,"out":"s","third":"a","tthird":"a","shot":1,"ahead":1,"gs":"w","pos":"RF","press":"mp","xp":0.939,"xt":0.0149,"byp":0,"phase":"fi","ch":"hl","x":-26.4,"y":-14.1,"xe":-29.9,"ye":-30.1,"to":"Jos\u00e9 Luis Cort\u00e9s"},{"n":"Jos\u00e9 Luis Cort\u00e9s","p":2,"min":85,"dir":"b","rng":"s","dist":9.0,"out":"s","third":"a","tthird":"a","shot":1,"gs":"w","pos":"LF","press":"lp","xp":0.997,"xt":0.0084,"byp":-2,"phase":"fi","ch":"wl","x":-30.3,"y":-30.9,"xe":-23.2,"ye":-25.3,"to":"Fede San Emeterio"},{"n":"Germ\u00e1n Novoa","p":2,"min":85,"dir":"sl","rng":"s","dist":10.1,"out":"s","third":"m","tthird":"m","shot":1,"gs":"w","pos":"RCB","press":"mp","xp":0.843,"xt":0.0123,"byp":1,"phase":"tr","ch":"hl","x":0.5,"y":-18.0,"xe":-3.4,"ye":-27.3,"to":"Jos\u00e9 Luis Cort\u00e9s"},{"n":"Jos\u00e9 Luis Cort\u00e9s","p":2,"min":85,"dir":"f","rng":"s","dist":10.1,"out":"s","third":"m","tthird":"m","shot":1,"ahead":1,"gs":"w","pos":"LF","press":"mp","xp":0.862,"xt":0.0094,"byp":2,"phase":"tr","ch":"wl","x":-3.0,"y":-25.3,"xe":-13.1,"ye":-25.2,"to":"Germ\u00e1n Novoa"},{"n":"Germ\u00e1n Novoa","p":2,"min":85,"dir":"sr","rng":"m","dist":15.3,"out":"s","third":"m","tthird":"m","one":1,"dng":1,"shot":1,"gs":"w","pos":"RCB","press":"mp","xp":0.926,"xt":0.0338,"byp":0,"phase":"tr","ch":"wl","x":-13.1,"y":-25.2,"xe":-14.5,"ye":-10.0,"to":"Borislav Ivanov Stankov"},{"n":"Fede San Emeterio","p":2,"min":88,"dir":"f","rng":"m","dist":18.9,"out":"s","third":"d","tthird":"d","one":1,"ahead":1,"gs":"w","pos":"CF","press":"mp","xp":0.862,"xt":0.0014,"byp":2,"phase":"ch","ch":"c","x":39.1,"y":5.0,"xe":25.1,"ye":17.6,"to":"Borja V\u00e1zquez"},{"n":"Borja V\u00e1zquez","p":2,"min":88,"tdir":"f","out":"u","third":"d","ahead":1,"diff":1,"gs":"w","pos":"RM","press":"mp","xp":0.535,"xt":0.0018,"byp":1,"phase":"ch","ch":"hr","x":14.1,"y":23.8,"xe":9.2,"ye":-20.0,"to":"Jos\u00e9 Luis Cort\u00e9s"},{"n":"Andr\u00e9s Prieto","p":2,"min":88,"tdir":"f","out":"u","third":"d","ahead":1,"gs":"w","pos":"GK","xp":0.692,"xt":0.01,"byp":9,"phase":"di","ch":"c","x":36.3,"y":-10.1,"xe":-10.1,"ye":-5.6,"to":"Jos\u00e9 Luis Cort\u00e9s"},{"n":"David And\u00fajar","p":2,"min":89,"dir":"b","rng":"m","dist":17.4,"out":"s","third":"m","tthird":"d","gs":"w","pos":"CM","press":"mp","xp":0.998,"byp":0,"phase":"bu","ch":"c","x":22.8,"y":0.3,"xe":40.0,"ye":-1.9,"to":"Andr\u00e9s Prieto"},{"n":"Andr\u00e9s Prieto","p":2,"min":89,"dir":"f","rng":"l","dist":51.1,"out":"s","third":"d","tthird":"m","high":1,"ahead":1,"gs":"w","pos":"GK","press":"lp","xp":0.712,"xt":0.0022,"byp":6,"phase":"di","ch":"c","x":38.9,"y":-1.4,"xe":-10.1,"ye":-15.8,"to":"Xemi Fern\u00e1ndez"},{"n":"David And\u00fajar","p":2,"min":89,"tdir":"b","out":"u","third":"d","ahead":1,"gs":"w","pos":"CM","press":"lp","xp":0.762,"xt":0.0012,"byp":4,"phase":"ch","ch":"c","x":37.3,"y":-7.6,"xe":7.5,"ye":-20.1,"to":"Xemi Fern\u00e1ndez"},{"n":"Andoni L\u00f3pez","p":2,"min":89,"tdir":"b","out":"u","third":"d","ahead":1,"diff":1,"gs":"w","pos":"LB","press":"hp","xp":0.533,"xt":0.0014,"byp":9,"phase":"di","ch":"hl","x":47.8,"y":-17.9,"xe":4.7,"ye":-23.6,"to":"Jos\u00e9 Luis Cort\u00e9s"},{"n":"Borja V\u00e1zquez","p":2,"min":92,"dir":"sl","rng":"s","dist":10.9,"out":"s","third":"m","tthird":"m","one":1,"gs":"w","pos":"RM","press":"np","xp":0.99,"xt":0.001,"byp":0,"phase":"cr","ch":"hr","x":7.6,"y":19.6,"xe":5.6,"ye":8.9,"to":"Fede San Emeterio"},{"n":"Fede San Emeterio","p":2,"min":92,"dir":"sr","rng":"s","dist":14.4,"out":"s","third":"m","tthird":"m","gs":"w","pos":"CF","press":"np","xp":0.996,"xt":0.0009,"byp":0,"phase":"cr","ch":"c","x":5.3,"y":9.3,"xe":7.5,"ye":23.5,"to":"Borja V\u00e1zquez"},{"n":"Borja V\u00e1zquez","p":2,"min":92,"dir":"sl","rng":"s","dist":7.8,"out":"s","third":"m","tthird":"m","ahead":1,"gs":"w","pos":"RM","press":"np","xp":0.954,"xt":0.0015,"byp":1,"phase":"cr","ch":"wr","x":7.9,"y":23.4,"xe":5.3,"ye":16.0,"to":"Eneko Undabarrena"},{"n":"Eneko Undabarrena","p":2,"min":92,"dir":"sr","rng":"s","dist":12.0,"out":"s","third":"m","tthird":"m","gs":"w","pos":"LCB","press":"lp","xp":0.982,"xt":0.001,"byp":0,"phase":"cr","ch":"hr","x":5.9,"y":16.8,"xe":8.1,"ye":28.6,"to":"Borja V\u00e1zquez"},{"n":"Xemi Fern\u00e1ndez","p":2,"min":94,"dir":"b","rng":"s","dist":6.0,"out":"s","third":"a","tthird":"a","gs":"w","pos":"LM","press":"hp","xp":0.821,"xt":0.0072,"byp":-6,"phase":"ch","ch":"wl","x":-49.5,"y":-29.0,"xe":-44.8,"ye":-32.6,"to":"Jos\u00e9 Luis Cort\u00e9s"},{"n":"Andoni L\u00f3pez","p":2,"min":96,"tdir":"sr","out":"u","third":"m","one":1,"gs":"w","pos":"LB","press":"hp","phase":"ch","ch":"hl","x":3.8,"y":-19.3,"xe":2.4,"ye":-10.5,"to":"Borislav Ivanov Stankov"},{"n":"Fede San Emeterio","p":2,"min":96,"tdir":"sl","out":"u","third":"m","ahead":1,"gs":"w","pos":"CF","press":"hp","xp":0.886,"xt":0.0049,"byp":2,"phase":"ds","ch":"hr","x":13.1,"y":2.2,"xe":5.9,"ye":-3.4,"to":"Jos\u00e9 Luis Cort\u00e9s"},{"n":"Borja V\u00e1zquez","p":2,"min":97,"dir":"sl","rng":"s","dist":10.8,"out":"s","third":"m","tthird":"a","gs":"w","pos":"RM","press":"mp","xp":0.909,"xt":0.0196,"byp":-3,"phase":"fi","ch":"wr","x":-28.1,"y":32.1,"xe":-27.3,"ye":21.4,"to":"Jos\u00e9 Luis Cort\u00e9s"}]